<?xml version="1.0" encoding="ASCII"?>
<!DOCTYPE nm:output SYSTEM "output.dtd">
<nm:output
xmlns:xsi="http://www.w3.org/2001/XMLSchema-instance"
xsi:schemaLocation="http://namespaces.oreilly.com/xmlnut/address output.xsd"
xmlns:nm="http://namespaces.oreilly.com/xmlnut/address"
>
<nm:start_datetime>2021-09-28T21:36:03.768</nm:start_datetime>
<nm:control_stream><![CDATA[
$PROB template control stream
;-----------------------------------------------------------------------
; Project: 	Investigating the contribution of residual unexplained
; 	   	variability in nonlinear mixed-effect approach
; Model: 	Two-compartment model with linear elimination
; Estim:	First-order conditional est. with interaction
; Author: 	Mutaz M. Jaber <jaber038@umn.edu>
; Date created: 9/7/2021
; Date modified: 9/7/2021
;-----------------------------------------------------------------------
$INPUT ID TIME DV AMT MDV EVID
$DATA ../../../../data/int/A1/dat15.csv ignore=@
$SUBR ADVAN4 TRANS4
$EST MET=1 NOABORT MAX=10000 PRINT=5 INTER NSIG=2
$PK
ET1 = EXP(ETA(1)*THETA(6))
ET2 = EXP(ETA(2)*THETA(7))
ET3 = EXP(ETA(3)*THETA(8))
ET4 = EXP(ETA(4)*THETA(9))
ET5 = EXP(ETA(5)*THETA(10))

CL = 5.0 * THETA(1) * ET1
V2 = 35  * THETA(2) * ET2
Q  = 50  * THETA(3) * ET3
V3 = 50  * THETA(4) * ET4
KA = 0.7 * THETA(5) * ET5
SC = V2
$ERROR
CVERR = 0.05
W = THETA(11)*F*CVERR

Y 	= F + W*ERR(1)

$THETA
(0,1) ; CL
(0,1) ; V2
(0,1) ; Q
(0,1) ; V3
(0,1) ; KA
(0,1) ; IIVCL
(0,1) ; IIVV2
(0,1) ; IIVQ
(0,1) ; IIVV3
(0,1) ; IIVKA
(0,1) ; CVPropErr

$OMEGA  (0.09 FIX)x5
$SIGMA  1 FIX ;        [P]
$COVARIANCE UNCOND
]]></nm:control_stream>
<nm:nmtran><![CDATA[

 WARNINGS AND ERRORS (IF ANY) FOR PROBLEM    1

 (WARNING  2) NM-TRAN INFERS THAT THE DATA ARE POPULATION.
]]></nm:nmtran>
<nm:nonmem nm:version='7.5.0'>
<nm:license_information><![CDATA[
License Registered to: University of Minnesota
Expiration Date:    14 APR 2022
Current Date:       28 SEP 2021
Days until program expires : 201
]]></nm:license_information>
<nm:program_information><![CDATA[
1NONLINEAR MIXED EFFECTS MODEL PROGRAM (NONMEM) VERSION 7.5.0
 ORIGINALLY DEVELOPED BY STUART BEAL, LEWIS SHEINER, AND ALISON BOECKMANN
 CURRENT DEVELOPERS ARE ROBERT BAUER, ICON DEVELOPMENT SOLUTIONS,
 AND ALISON BOECKMANN. IMPLEMENTATION, EFFICIENCY, AND STANDARDIZATION
 PERFORMED BY NOUS INFOSYSTEMS.
]]></nm:program_information>
<nm:problem nm:number='1' nm:subproblem='0' nm:superproblem1='0' nm:iteration1='0' nm:superproblem2='0' nm:iteration2='0'>
<nm:problem_title>template control stream</nm:problem_title>
<nm:problem_information><![CDATA[

 PROBLEM NO.:         1
 template control stream
0DATA CHECKOUT RUN:              NO
 DATA SET LOCATED ON UNIT NO.:    2
 THIS UNIT TO BE REWOUND:        NO
 NO. OF DATA RECS IN DATA SET:     1000
 NO. OF DATA ITEMS IN DATA SET:   6
 ID DATA ITEM IS DATA ITEM NO.:   1
 DEP VARIABLE IS DATA ITEM NO.:   3
 MDV DATA ITEM IS DATA ITEM NO.:  5
0INDICES PASSED TO SUBROUTINE PRED:
   6   2   4   0   0   0   0   0   0   0   0
0LABELS FOR DATA ITEMS:
 ID TIME DV AMT MDV EVID
0FORMAT FOR DATA:
 (2E4.0,E20.0,E4.0,2E2.0)

 TOT. NO. OF OBS RECS:      900
 TOT. NO. OF INDIVIDUALS:      100
0LENGTH OF THETA:  11
0DEFAULT THETA BOUNDARY TEST OMITTED:    NO
0OMEGA HAS SIMPLE DIAGONAL FORM WITH DIMENSION:   5
0DEFAULT OMEGA BOUNDARY TEST OMITTED:    NO
0SIGMA HAS SIMPLE DIAGONAL FORM WITH DIMENSION:   1
0DEFAULT SIGMA BOUNDARY TEST OMITTED:    NO
0INITIAL ESTIMATE OF THETA:
 LOWER BOUND    INITIAL EST    UPPER BOUND
  0.0000E+00     0.1000E+01     0.1000E+07
  0.0000E+00     0.1000E+01     0.1000E+07
  0.0000E+00     0.1000E+01     0.1000E+07
  0.0000E+00     0.1000E+01     0.1000E+07
  0.0000E+00     0.1000E+01     0.1000E+07
  0.0000E+00     0.1000E+01     0.1000E+07
  0.0000E+00     0.1000E+01     0.1000E+07
  0.0000E+00     0.1000E+01     0.1000E+07
  0.0000E+00     0.1000E+01     0.1000E+07
  0.0000E+00     0.1000E+01     0.1000E+07
  0.0000E+00     0.1000E+01     0.1000E+07
0INITIAL ESTIMATE OF OMEGA:
 0.9000E-01
 0.0000E+00   0.9000E-01
 0.0000E+00   0.0000E+00   0.9000E-01
 0.0000E+00   0.0000E+00   0.0000E+00   0.9000E-01
 0.0000E+00   0.0000E+00   0.0000E+00   0.0000E+00   0.9000E-01
0OMEGA CONSTRAINED TO BE THIS INITIAL ESTIMATE
0INITIAL ESTIMATE OF SIGMA:
 0.1000E+01
0SIGMA CONSTRAINED TO BE THIS INITIAL ESTIMATE
0COVARIANCE STEP OMITTED:        NO
 EIGENVLS. PRINTED:              NO
 SPECIAL COMPUTATION:            NO
 COMPRESSED FORMAT:              NO
 GRADIENT METHOD USED:     NOSLOW
 SIGDIGITS ETAHAT (SIGLO):                  -1
 SIGDIGITS GRADIENTS (SIGL):                -1
 EXCLUDE COV FOR FOCE (NOFCOV):              NO
 Cholesky Transposition of R Matrix (CHOLROFF):0
 KNUTHSUMOFF:                                -1
 RESUME COV ANALYSIS (RESUME):               NO
 SIR SAMPLE SIZE (SIRSAMPLE):
 NON-LINEARLY TRANSFORM THETAS DURING COV (THBND): 1
 PRECONDTIONING CYCLES (PRECOND):        0
 PRECONDTIONING TYPES (PRECONDS):        TOS
 FORCED PRECONDTIONING CYCLES (PFCOND):0
 PRECONDTIONING TYPE (PRETYPE):        0
 FORCED POS. DEFINITE SETTING DURING PRECONDITIONING: (FPOSDEF):0
 SIMPLE POS. DEFINITE SETTING: (POSDEF):-1
1DOUBLE PRECISION PREDPP VERSION 7.5.0

 TWO COMPARTMENT MODEL WITH FIRST-ORDER ABSORPTION (ADVAN4)
0MAXIMUM NO. OF BASIC PK PARAMETERS:   5
0BASIC PK PARAMETERS (AFTER TRANSLATION):
   BASIC PK PARAMETER NO.  1: ELIMINATION RATE (K)
   BASIC PK PARAMETER NO.  2: CENTRAL-TO-PERIPH. RATE (K23)
   BASIC PK PARAMETER NO.  3: PERIPH.-TO-CENTRAL RATE (K32)
   BASIC PK PARAMETER NO.  5: ABSORPTION RATE (KA)
 TRANSLATOR WILL CONVERT PARAMETERS
 CL, V2, Q, V3 TO K, K23, K32 (TRANS4)
0COMPARTMENT ATTRIBUTES
 COMPT. NO.   FUNCTION   INITIAL    ON/OFF      DOSE      DEFAULT    DEFAULT
                         STATUS     ALLOWED    ALLOWED    FOR DOSE   FOR OBS.
    1         DEPOT        OFF        YES        YES        YES        NO
    2         CENTRAL      ON         NO         YES        NO         YES
    3         PERIPH.      ON         NO         YES        NO         NO
    4         OUTPUT       OFF        YES        NO         NO         NO
1
 ADDITIONAL PK PARAMETERS - ASSIGNMENT OF ROWS IN GG
 COMPT. NO.                             INDICES
              SCALE      BIOAVAIL.   ZERO-ORDER  ZERO-ORDER  ABSORB
                         FRACTION    RATE        DURATION    LAG
    1            *           *           *           *           *
    2            6           *           *           *           *
    3            *           *           *           *           *
    4            *           -           -           -           -
             - PARAMETER IS NOT ALLOWED FOR THIS MODEL
             * PARAMETER IS NOT SUPPLIED BY PK SUBROUTINE;
               WILL DEFAULT TO ONE IF APPLICABLE
0DATA ITEM INDICES USED BY PRED ARE:
   EVENT ID DATA ITEM IS DATA ITEM NO.:      6
   TIME DATA ITEM IS DATA ITEM NO.:          2
   DOSE AMOUNT DATA ITEM IS DATA ITEM NO.:   4

0PK SUBROUTINE CALLED WITH EVERY EVENT RECORD.
 PK SUBROUTINE NOT CALLED AT NONEVENT (ADDITIONAL OR LAGGED) DOSE TIMES.
0ERROR SUBROUTINE CALLED WITH EVERY EVENT RECORD.
]]></nm:problem_information>
<nm:problem_options
 nm:data_checkout_run='no' nm:data_unit='2' nm:data_rewind='no' nm:data_nrec='1000' nm:data_nitems='6' nm:data_id='1'
 nm:data_l2='0' nm:data_dv='3' nm:data_mdv='5' nm:data_mrg='0' nm:data_raw='0' nm:data_rpt='0' nm:data_sub_array1='0'
 nm:data_sub_array2='0' nm:data_sub_array3='0' nm:data_pred_indices='6,2,4,0,0,0,0,0,0,0,0'
 nm:data_format='(2e4.0,e20.0,e4.0,2e2.0)' nm:data_nobs='900' nm:data_nind='100' nm:data_mdv100='0' nm:nthetat='11'
 nm:theta_bound_test_omitted='no' nm:omega_diagdim='5' nm:omega_bound_test_omitted='no' nm:sigma_diagdim='1'
 nm:sigma_bound_test_omitted='no' nm:cov_omitted='no' nm:cov_matrix='rsr' nm:cov_eigen_print='no'
 nm:cov_special='no' nm:cov_compressed='no' nm:cov_slow_gradient='noslow' nm:cov_siglocov='-1' nm:cov_siglcov='-1'
 nm:cov_tol='-1' nm:cov_atol='-1' nm:cov_nofcov='no' nm:cov_cholroff='0' nm:cov_knuthsumoff='-1' nm:cov_resume='no'
 nm:cov_sirsample='BLANK' nm:cov_thbnd='1' nm:cov_precond='0' nm:cov_preconds='tos' nm:cov_pfcond='0'
 nm:cov_pretype='0' nm:cov_fposdef='0' nm:cov_posdef='-1' nm:pred_advan='4' nm:pred_evid='6' nm:pred_time='2'
 nm:pred_amt='4'
/>
<nm:theta_lb>
<nm:val nm:name='1'>0.0000000000000000</nm:val>
<nm:val nm:name='2'>0.0000000000000000</nm:val>
<nm:val nm:name='3'>0.0000000000000000</nm:val>
<nm:val nm:name='4'>0.0000000000000000</nm:val>
<nm:val nm:name='5'>0.0000000000000000</nm:val>
<nm:val nm:name='6'>0.0000000000000000</nm:val>
<nm:val nm:name='7'>0.0000000000000000</nm:val>
<nm:val nm:name='8'>0.0000000000000000</nm:val>
<nm:val nm:name='9'>0.0000000000000000</nm:val>
<nm:val nm:name='10'>0.0000000000000000</nm:val>
<nm:val nm:name='11'>0.0000000000000000</nm:val>
</nm:theta_lb>
<nm:theta_in>
<nm:val nm:name='1'>1.0000000000000000</nm:val>
<nm:val nm:name='2'>1.0000000000000000</nm:val>
<nm:val nm:name='3'>1.0000000000000000</nm:val>
<nm:val nm:name='4'>1.0000000000000000</nm:val>
<nm:val nm:name='5'>1.0000000000000000</nm:val>
<nm:val nm:name='6'>1.0000000000000000</nm:val>
<nm:val nm:name='7'>1.0000000000000000</nm:val>
<nm:val nm:name='8'>1.0000000000000000</nm:val>
<nm:val nm:name='9'>1.0000000000000000</nm:val>
<nm:val nm:name='10'>1.0000000000000000</nm:val>
<nm:val nm:name='11'>1.0000000000000000</nm:val>
</nm:theta_in>
<nm:theta_ub>
<nm:val nm:name='1'>1000000.0000000000</nm:val>
<nm:val nm:name='2'>1000000.0000000000</nm:val>
<nm:val nm:name='3'>1000000.0000000000</nm:val>
<nm:val nm:name='4'>1000000.0000000000</nm:val>
<nm:val nm:name='5'>1000000.0000000000</nm:val>
<nm:val nm:name='6'>1000000.0000000000</nm:val>
<nm:val nm:name='7'>1000000.0000000000</nm:val>
<nm:val nm:name='8'>1000000.0000000000</nm:val>
<nm:val nm:name='9'>1000000.0000000000</nm:val>
<nm:val nm:name='10'>1000000.0000000000</nm:val>
<nm:val nm:name='11'>1000000.0000000000</nm:val>
</nm:theta_ub>
<nm:estimation nm:number='1' nm:type='0'>
<nm:table_series>1</nm:table_series>
<nm:estimation_method>focei</nm:estimation_method>
<nm:estimation_title>First Order Conditional Estimation with Interaction</nm:estimation_title>
<nm:estimation_information><![CDATA[
 ESTIMATION STEP OMITTED:                 NO
 ANALYSIS TYPE:                           POPULATION
 NUMBER OF SADDLE POINT RESET ITERATIONS:      0
 GRADIENT METHOD USED:               NOSLOW
 CONDITIONAL ESTIMATES USED:              YES
 CENTERED ETA:                            NO
 EPS-ETA INTERACTION:                     YES
 LAPLACIAN OBJ. FUNC.:                    NO
 NO. OF FUNCT. EVALS. ALLOWED:            10000
 NO. OF SIG. FIGURES REQUIRED:            2
 INTERMEDIATE PRINTOUT:                   YES
 ESTIMATE OUTPUT TO MSF:                  NO
 ABORT WITH PRED EXIT CODE 1:             NO
 IND. OBJ. FUNC. VALUES SORTED:           NO
 NUMERICAL DERIVATIVE
       FILE REQUEST (NUMDER):               NONE
 MAP (ETAHAT) ESTIMATION METHOD (OPTMAP):   0
 ETA HESSIAN EVALUATION METHOD (ETADER):    0
 INITIAL ETA FOR MAP ESTIMATION (MCETA):    0
 SIGDIGITS FOR MAP ESTIMATION (SIGLO):      100
 GRADIENT SIGDIGITS OF
       FIXED EFFECTS PARAMETERS (SIGL):     100
 NOPRIOR SETTING (NOPRIOR):                 0
 NOCOV SETTING (NOCOV):                     OFF
 DERCONT SETTING (DERCONT):                 OFF
 FINAL ETA RE-EVALUATION (FNLETA):          1
 EXCLUDE NON-INFLUENTIAL (NON-INFL.) ETAS
       IN SHRINKAGE (ETASTYPE):             NO
 NON-INFL. ETA CORRECTION (NONINFETA):      0
 RAW OUTPUT FILE (FILE): m15.ext
 EXCLUDE TITLE (NOTITLE):                   NO
 EXCLUDE COLUMN LABELS (NOLABEL):           NO
 FORMAT FOR ADDITIONAL FILES (FORMAT):      S1PE12.5
 PARAMETER ORDER FOR OUTPUTS (ORDER):       TSOL
 KNUTHSUMOFF:                               0
 INCLUDE LNTWOPI:                           NO
 INCLUDE CONSTANT TERM TO PRIOR (PRIORC):   NO
 INCLUDE CONSTANT TERM TO OMEGA (ETA) (OLNTWOPI):NO
 ADDITIONAL CONVERGENCE TEST (CTYPE=4)?:    NO
 EM OR BAYESIAN METHOD USED:                 NONE

]]></nm:estimation_information>
<nm:estimation_options
 nm:estim_omitted='no' nm:analysis_type='pop' nm:saddle_reset='0' nm:saddle_hess='0' nm:slow_gradient='noslow'
 nm:cond_estim='yes' nm:centered_eta='no' nm:epseta_interaction='yes' nm:laplace='no' nm:predflag='0' nm:maxfn='10000'
 nm:nsig='2' nm:msfo='no' nm:abort='no' nm:objsort='no' nm:numder='0' nm:optmap='0' nm:etader='0' nm:mceta='0' nm:siglo='100'
 nm:sigl='100' nm:noprior='0' nm:nocov='0' nm:dercont='0' nm:atol='0' nm:fnleta='1' nm:etastype='0' nm:noninfeta='0'
 nm:file='m15.ext' nm:notitle='0' nm:nolabel='0' nm:format='s1pe12.5' nm:order='tsol' nm:knuthsumoff='0' nm:lntwopi='0'
 nm:priorc='0' nm:olntwopi='0' nm:ctype='0'
/>
<nm:monitor>
<nm:obj nm:iteration='0'>-3521.2665965901624</nm:obj>
<nm:obj nm:iteration='5'>-3618.2824716750015</nm:obj>
<nm:obj nm:iteration='10'>-3618.8315751905120</nm:obj>
<nm:obj nm:iteration='15'>-3620.3184256680674</nm:obj>
<nm:obj nm:iteration='19'>-3620.3209475807744</nm:obj>
</nm:monitor>
<nm:termination_status>0</nm:termination_status>
<nm:termination_nfuncevals>634</nm:termination_nfuncevals>
<nm:termination_sigdigits>2.2590698962339206</nm:termination_sigdigits>
<nm:termination_information><![CDATA[
0MINIMIZATION SUCCESSFUL
 NO. OF FUNCTION EVALUATIONS USED:      634
 NO. OF SIG. DIGITS IN FINAL EST.:  2.3
]]></nm:termination_information>
<nm:termination_txtmsg>
<nm:val nm:name='1'>37</nm:val>
</nm:termination_txtmsg>
<nm:etabar>
<nm:row nm:rname='SUBPOP1'>
<nm:col nm:cname='ETA1'>5.7631883311074720E-004</nm:col>
<nm:col nm:cname='ETA2'>-2.5320310016074297E-002</nm:col>
<nm:col nm:cname='ETA3'>-1.8460145762919381E-002</nm:col>
<nm:col nm:cname='ETA4'>1.2776942432159348E-002</nm:col>
<nm:col nm:cname='ETA5'>-2.7215742516071000E-002</nm:col>
</nm:row>
</nm:etabar>
<nm:etabarse>
<nm:row nm:rname='SUBPOP1'>
<nm:col nm:cname='ETA1'>2.9820323486907708E-002</nm:col>
<nm:col nm:cname='ETA2'>2.3045359355980684E-002</nm:col>
<nm:col nm:cname='ETA3'>1.6495704417881563E-002</nm:col>
<nm:col nm:cname='ETA4'>2.7629703946107250E-002</nm:col>
<nm:col nm:cname='ETA5'>2.3782632316291998E-002</nm:col>
</nm:row>
</nm:etabarse>
<nm:etabarn>
<nm:row nm:rname='SUBPOP1'>
<nm:col nm:cname='ETA1'>100</nm:col>
<nm:col nm:cname='ETA2'>100</nm:col>
<nm:col nm:cname='ETA3'>100</nm:col>
<nm:col nm:cname='ETA4'>100</nm:col>
<nm:col nm:cname='ETA5'>100</nm:col>
</nm:row>
</nm:etabarn>
<nm:etabarpval>
<nm:row nm:rname='SUBPOP1'>
<nm:col nm:cname='ETA1'>0.98458066088878782</nm:col>
<nm:col nm:cname='ETA2'>0.27189194715129117</nm:col>
<nm:col nm:cname='ETA3'>0.26310266654872499</nm:col>
<nm:col nm:cname='ETA4'>0.64376942460732600</nm:col>
<nm:col nm:cname='ETA5'>0.25247709800928558</nm:col>
</nm:row>
</nm:etabarpval>
<nm:etashrinksd>
<nm:row nm:rname='SUBPOP1'>
<nm:col nm:cname='ETA1'>9.8157441317692218E-002</nm:col>
<nm:col nm:cname='ETA2'>22.795141270005757</nm:col>
<nm:col nm:cname='ETA3'>44.737310902301942</nm:col>
<nm:col nm:cname='ETA4'>7.4370090324851308</nm:col>
<nm:col nm:cname='ETA5'>20.325183919069190</nm:col>
</nm:row>
</nm:etashrinksd>
<nm:etashrinkvr>
<nm:row nm:rname='SUBPOP1'>
<nm:col nm:cname='ETA1'>0.19621853380251686</nm:col>
<nm:col nm:cname='ETA2'>40.394097884816325</nm:col>
<nm:col nm:cname='ETA3'>69.460351936911636</nm:col>
<nm:col nm:cname='ETA4'>14.320927031477604</nm:col>
<nm:col nm:cname='ETA5'>36.519236824698496</nm:col>
</nm:row>
</nm:etashrinkvr>
<nm:ebvshrinksd>
<nm:row nm:rname='SUBPOP1'>
<nm:col nm:cname='EBV1'>0.49383825300796103</nm:col>
<nm:col nm:cname='EBV2'>22.659233828448023</nm:col>
<nm:col nm:cname='EBV3'>45.550630929122867</nm:col>
<nm:col nm:cname='EBV4'>7.9627870293932030</nm:col>
<nm:col nm:cname='EBV5'>20.300548292098387</nm:col>
</nm:row>
</nm:ebvshrinksd>
<nm:ebvshrinkvr>
<nm:row nm:rname='SUBPOP1'>
<nm:col nm:cname='EBV1'>0.98523774381458551</nm:col>
<nm:col nm:cname='EBV2'>40.184058879973207</nm:col>
<nm:col nm:cname='EBV3'>70.352662077834097</nm:col>
<nm:col nm:cname='EBV4'>15.291514286031669</nm:col>
<nm:col nm:cname='EBV5'>36.479973974598579</nm:col>
</nm:row>
</nm:ebvshrinkvr>
<nm:relativeinf>
<nm:row nm:rname='SUBPOP1'>
<nm:col nm:cname='REL1'>99.006309750848189</nm:col>
<nm:col nm:cname='REL2'>26.062141008358505</nm:col>
<nm:col nm:cname='REL3'>17.542281532295299</nm:col>
<nm:col nm:cname='REL4'>56.196786912218279</nm:col>
<nm:col nm:cname='REL5'>21.796353640355992</nm:col>
</nm:row>
</nm:relativeinf>
<nm:epsshrinksd>
<nm:row nm:rname='SUBPOP1'>
<nm:col nm:cname='EPS1'>20.742911710050439</nm:col>
</nm:row>
</nm:epsshrinksd>
<nm:epsshrinkvr>
<nm:row nm:rname='SUBPOP1'>
<nm:col nm:cname='EPS1'>37.183139557991396</nm:col>
</nm:row>
</nm:epsshrinkvr>
<nm:estimation_elapsed_time>16.25</nm:estimation_elapsed_time>
<nm:covariance_information><![CDATA[
]]></nm:covariance_information>
<nm:covariance_status nm:error='0' nm:numnegeigenvalues='-1' nm:mineigenvalue='0.0000000000000000' nm:maxeigenvalue='0.0000000000000000' nm:rms='0.0000000000000000'/>
<nm:covariance_elapsed_time>12.03</nm:covariance_elapsed_time>
<nm:final_objective_function_text>MINIMUM VALUE OF OBJECTIVE FUNCTION</nm:final_objective_function_text>
<nm:final_objective_function>-3620.3209475807744</nm:final_objective_function>
<nm:theta>
<nm:val nm:name='1'>1.0436358036666864</nm:val>
<nm:val nm:name='2'>0.99246702686404265</nm:val>
<nm:val nm:name='3'>0.90052148671343835</nm:val>
<nm:val nm:name='4'>1.0639659597226587</nm:val>
<nm:val nm:name='5'>0.90487922952733946</nm:val>
<nm:val nm:name='6'>0.93507761277135859</nm:val>
<nm:val nm:name='7'>1.1601054367331780</nm:val>
<nm:val nm:name='8'>0.90756721240507110</nm:val>
<nm:val nm:name='9'>1.0753453050909256</nm:val>
<nm:val nm:name='10'>1.0149379260845417</nm:val>
<nm:val nm:name='11'>1.2981136230984340</nm:val>
</nm:theta>
<nm:omega>
<nm:row nm:rname='1'>
<nm:col nm:cname='1'>8.9999999999999997E-002</nm:col>
</nm:row>
<nm:row nm:rname='2'>
<nm:col nm:cname='1'>0.0000000000000000</nm:col>
<nm:col nm:cname='2'>8.9999999999999997E-002</nm:col>
</nm:row>
<nm:row nm:rname='3'>
<nm:col nm:cname='1'>0.0000000000000000</nm:col>
<nm:col nm:cname='2'>0.0000000000000000</nm:col>
<nm:col nm:cname='3'>8.9999999999999997E-002</nm:col>
</nm:row>
<nm:row nm:rname='4'>
<nm:col nm:cname='1'>0.0000000000000000</nm:col>
<nm:col nm:cname='2'>0.0000000000000000</nm:col>
<nm:col nm:cname='3'>0.0000000000000000</nm:col>
<nm:col nm:cname='4'>8.9999999999999997E-002</nm:col>
</nm:row>
<nm:row nm:rname='5'>
<nm:col nm:cname='1'>0.0000000000000000</nm:col>
<nm:col nm:cname='2'>0.0000000000000000</nm:col>
<nm:col nm:cname='3'>0.0000000000000000</nm:col>
<nm:col nm:cname='4'>0.0000000000000000</nm:col>
<nm:col nm:cname='5'>8.9999999999999997E-002</nm:col>
</nm:row>
</nm:omega>
<nm:sigma>
<nm:row nm:rname='1'>
<nm:col nm:cname='1'>1.0000000000000000</nm:col>
</nm:row>
</nm:sigma>
<nm:omegac>
<nm:row nm:rname='1'>
<nm:col nm:cname='1'>0.29999999999999999</nm:col>
</nm:row>
<nm:row nm:rname='2'>
<nm:col nm:cname='1'>0.0000000000000000</nm:col>
<nm:col nm:cname='2'>0.29999999999999999</nm:col>
</nm:row>
<nm:row nm:rname='3'>
<nm:col nm:cname='1'>0.0000000000000000</nm:col>
<nm:col nm:cname='2'>0.0000000000000000</nm:col>
<nm:col nm:cname='3'>0.29999999999999999</nm:col>
</nm:row>
<nm:row nm:rname='4'>
<nm:col nm:cname='1'>0.0000000000000000</nm:col>
<nm:col nm:cname='2'>0.0000000000000000</nm:col>
<nm:col nm:cname='3'>0.0000000000000000</nm:col>
<nm:col nm:cname='4'>0.29999999999999999</nm:col>
</nm:row>
<nm:row nm:rname='5'>
<nm:col nm:cname='1'>0.0000000000000000</nm:col>
<nm:col nm:cname='2'>0.0000000000000000</nm:col>
<nm:col nm:cname='3'>0.0000000000000000</nm:col>
<nm:col nm:cname='4'>0.0000000000000000</nm:col>
<nm:col nm:cname='5'>0.29999999999999999</nm:col>
</nm:row>
</nm:omegac>
<nm:sigmac>
<nm:row nm:rname='1'>
<nm:col nm:cname='1'>1.0000000000000000</nm:col>
</nm:row>
</nm:sigmac>
<nm:thetase>
<nm:val nm:name='1'>2.9663721425085367E-002</nm:val>
<nm:val nm:name='2'>0.13848779278471979</nm:val>
<nm:val nm:name='3'>0.13374270858330436</nm:val>
<nm:val nm:name='4'>6.2031574325016839E-002</nm:val>
<nm:val nm:name='5'>0.13400739715566240</nm:val>
<nm:val nm:name='6'>7.7370772724944664E-002</nm:val>
<nm:val nm:name='7'>0.17370760952290559</nm:val>
<nm:val nm:name='8'>0.26664197990467470</nm:val>
<nm:val nm:name='9'>0.13565709222120861</nm:val>
<nm:val nm:name='10'>0.10666655305111510</nm:val>
<nm:val nm:name='11'>5.8229388064758893E-002</nm:val>
</nm:thetase>
<nm:omegase>
<nm:row nm:rname='1'>
<nm:col nm:cname='1'>10000000000.000000</nm:col>
</nm:row>
<nm:row nm:rname='2'>
<nm:col nm:cname='1'>10000000000.000000</nm:col>
<nm:col nm:cname='2'>10000000000.000000</nm:col>
</nm:row>
<nm:row nm:rname='3'>
<nm:col nm:cname='1'>10000000000.000000</nm:col>
<nm:col nm:cname='2'>10000000000.000000</nm:col>
<nm:col nm:cname='3'>10000000000.000000</nm:col>
</nm:row>
<nm:row nm:rname='4'>
<nm:col nm:cname='1'>10000000000.000000</nm:col>
<nm:col nm:cname='2'>10000000000.000000</nm:col>
<nm:col nm:cname='3'>10000000000.000000</nm:col>
<nm:col nm:cname='4'>10000000000.000000</nm:col>
</nm:row>
<nm:row nm:rname='5'>
<nm:col nm:cname='1'>10000000000.000000</nm:col>
<nm:col nm:cname='2'>10000000000.000000</nm:col>
<nm:col nm:cname='3'>10000000000.000000</nm:col>
<nm:col nm:cname='4'>10000000000.000000</nm:col>
<nm:col nm:cname='5'>10000000000.000000</nm:col>
</nm:row>
</nm:omegase>
<nm:sigmase>
<nm:row nm:rname='1'>
<nm:col nm:cname='1'>10000000000.000000</nm:col>
</nm:row>
</nm:sigmase>
<nm:omegacse>
<nm:row nm:rname='1'>
<nm:col nm:cname='1'>10000000000.000000</nm:col>
</nm:row>
<nm:row nm:rname='2'>
<nm:col nm:cname='1'>10000000000.000000</nm:col>
<nm:col nm:cname='2'>10000000000.000000</nm:col>
</nm:row>
<nm:row nm:rname='3'>
<nm:col nm:cname='1'>10000000000.000000</nm:col>
<nm:col nm:cname='2'>10000000000.000000</nm:col>
<nm:col nm:cname='3'>10000000000.000000</nm:col>
</nm:row>
<nm:row nm:rname='4'>
<nm:col nm:cname='1'>10000000000.000000</nm:col>
<nm:col nm:cname='2'>10000000000.000000</nm:col>
<nm:col nm:cname='3'>10000000000.000000</nm:col>
<nm:col nm:cname='4'>10000000000.000000</nm:col>
</nm:row>
<nm:row nm:rname='5'>
<nm:col nm:cname='1'>10000000000.000000</nm:col>
<nm:col nm:cname='2'>10000000000.000000</nm:col>
<nm:col nm:cname='3'>10000000000.000000</nm:col>
<nm:col nm:cname='4'>10000000000.000000</nm:col>
<nm:col nm:cname='5'>10000000000.000000</nm:col>
</nm:row>
</nm:omegacse>
<nm:sigmacse>
<nm:row nm:rname='1'>
<nm:col nm:cname='1'>10000000000.000000</nm:col>
</nm:row>
</nm:sigmacse>
<nm:covariance>
<nm:row nm:rname='THETA1'>
<nm:col nm:cname='THETA1'>8.7993636878506856E-004</nm:col>
</nm:row>
<nm:row nm:rname='THETA2'>
<nm:col nm:cname='THETA1'>-1.8172706728585141E-004</nm:col>
<nm:col nm:cname='THETA2'>1.9178868750383486E-002</nm:col>
</nm:row>
<nm:row nm:rname='THETA3'>
<nm:col nm:cname='THETA1'>-3.7223589416288973E-004</nm:col>
<nm:col nm:cname='THETA2'>1.6633712259302911E-002</nm:col>
<nm:col nm:cname='THETA3'>1.7887112099198674E-002</nm:col>
</nm:row>
<nm:row nm:rname='THETA4'>
<nm:col nm:cname='THETA1'>1.1214026995191102E-004</nm:col>
<nm:col nm:cname='THETA2'>-7.0086753062148449E-003</nm:col>
<nm:col nm:cname='THETA3'>-6.0280488157166334E-003</nm:col>
<nm:col nm:cname='THETA4'>3.8479162132400882E-003</nm:col>
</nm:row>
<nm:row nm:rname='THETA5'>
<nm:col nm:cname='THETA1'>-3.7447491280260837E-004</nm:col>
<nm:col nm:cname='THETA2'>1.7575780728210727E-002</nm:col>
<nm:col nm:cname='THETA3'>1.6778102841282831E-002</nm:col>
<nm:col nm:cname='THETA4'>-6.6259238725873068E-003</nm:col>
<nm:col nm:cname='THETA5'>1.7957982492435437E-002</nm:col>
</nm:row>
<nm:row nm:rname='THETA6'>
<nm:col nm:cname='THETA1'>-7.6938600009934127E-004</nm:col>
<nm:col nm:cname='THETA2'>-4.1045626906518719E-005</nm:col>
<nm:col nm:cname='THETA3'>-6.8541820016320993E-005</nm:col>
<nm:col nm:cname='THETA4'>-1.0276799927034552E-004</nm:col>
<nm:col nm:cname='THETA5'>6.4899593110572960E-005</nm:col>
<nm:col nm:cname='THETA6'>5.9862364720550416E-003</nm:col>
</nm:row>
<nm:row nm:rname='THETA7'>
<nm:col nm:cname='THETA1'>3.9561081195406406E-004</nm:col>
<nm:col nm:cname='THETA2'>-1.7597604755378700E-002</nm:col>
<nm:col nm:cname='THETA3'>-1.6369951796039471E-002</nm:col>
<nm:col nm:cname='THETA4'>5.4118306021616767E-003</nm:col>
<nm:col nm:cname='THETA5'>-1.7443491975399360E-002</nm:col>
<nm:col nm:cname='THETA6'>-7.7200611590513770E-004</nm:col>
<nm:col nm:cname='THETA7'>3.0174333606162246E-002</nm:col>
</nm:row>
<nm:row nm:rname='THETA8'>
<nm:col nm:cname='THETA1'>-8.5131204349383279E-004</nm:col>
<nm:col nm:cname='THETA2'>3.0088389250202560E-002</nm:col>
<nm:col nm:cname='THETA3'>3.0270982800057654E-002</nm:col>
<nm:col nm:cname='THETA4'>-1.0421264535674360E-002</nm:col>
<nm:col nm:cname='THETA5'>3.0267763667501692E-002</nm:col>
<nm:col nm:cname='THETA6'>-8.7282493197097198E-004</nm:col>
<nm:col nm:cname='THETA7'>-2.9560704488344212E-002</nm:col>
<nm:col nm:cname='THETA8'>7.1097945447484948E-002</nm:col>
</nm:row>
<nm:row nm:rname='THETA9'>
<nm:col nm:cname='THETA1'>-4.1203551999628539E-004</nm:col>
<nm:col nm:cname='THETA2'>2.6619818979814348E-003</nm:col>
<nm:col nm:cname='THETA3'>3.6382290157661638E-003</nm:col>
<nm:col nm:cname='THETA4'>3.0222847231725457E-004</nm:col>
<nm:col nm:cname='THETA5'>3.3284942146615351E-003</nm:col>
<nm:col nm:cname='THETA6'>-4.6184262064522062E-004</nm:col>
<nm:col nm:cname='THETA7'>1.0985263611639909E-003</nm:col>
<nm:col nm:cname='THETA8'>1.0310042437963849E-002</nm:col>
<nm:col nm:cname='THETA9'>1.8402846669913500E-002</nm:col>
</nm:row>
<nm:row nm:rname='THETA10'>
<nm:col nm:cname='THETA1'>-3.2399095895833583E-004</nm:col>
<nm:col nm:cname='THETA2'>5.1423055269263140E-003</nm:col>
<nm:col nm:cname='THETA3'>4.8316043789202135E-003</nm:col>
<nm:col nm:cname='THETA4'>-1.7026327282774136E-003</nm:col>
<nm:col nm:cname='THETA5'>5.0280610750432705E-003</nm:col>
<nm:col nm:cname='THETA6'>-1.9744815448737561E-004</nm:col>
<nm:col nm:cname='THETA7'>-2.0462376934883104E-003</nm:col>
<nm:col nm:cname='THETA8'>1.2291185690317025E-002</nm:col>
<nm:col nm:cname='THETA9'>1.1234089567128934E-003</nm:col>
<nm:col nm:cname='THETA10'>1.1377753539806352E-002</nm:col>
</nm:row>
<nm:row nm:rname='THETA11'>
<nm:col nm:cname='THETA1'>6.6887974642539235E-004</nm:col>
<nm:col nm:cname='THETA2'>-3.7535840613999961E-003</nm:col>
<nm:col nm:cname='THETA3'>-4.0865282442790292E-003</nm:col>
<nm:col nm:cname='THETA4'>1.3281523512494147E-003</nm:col>
<nm:col nm:cname='THETA5'>-3.8342397493912293E-003</nm:col>
<nm:col nm:cname='THETA6'>1.1205420826829448E-004</nm:col>
<nm:col nm:cname='THETA7'>3.8758063440530264E-003</nm:col>
<nm:col nm:cname='THETA8'>-8.6203137354940625E-003</nm:col>
<nm:col nm:cname='THETA9'>-9.8675537367383815E-004</nm:col>
<nm:col nm:cname='THETA10'>-9.3706320090128337E-004</nm:col>
<nm:col nm:cname='THETA11'>3.3906616343962852E-003</nm:col>
</nm:row>
<nm:row nm:rname='OMEGA(1,1)'>
<nm:col nm:cname='THETA1'>0.0000000000000000</nm:col>
<nm:col nm:cname='THETA2'>0.0000000000000000</nm:col>
<nm:col nm:cname='THETA3'>0.0000000000000000</nm:col>
<nm:col nm:cname='THETA4'>0.0000000000000000</nm:col>
<nm:col nm:cname='THETA5'>0.0000000000000000</nm:col>
<nm:col nm:cname='THETA6'>0.0000000000000000</nm:col>
<nm:col nm:cname='THETA7'>0.0000000000000000</nm:col>
<nm:col nm:cname='THETA8'>0.0000000000000000</nm:col>
<nm:col nm:cname='THETA9'>0.0000000000000000</nm:col>
<nm:col nm:cname='THETA10'>0.0000000000000000</nm:col>
<nm:col nm:cname='THETA11'>0.0000000000000000</nm:col>
<nm:col nm:cname='OMEGA(1,1)'>0.0000000000000000</nm:col>
</nm:row>
<nm:row nm:rname='OMEGA(1,2)'>
<nm:col nm:cname='THETA1'>0.0000000000000000</nm:col>
<nm:col nm:cname='THETA2'>0.0000000000000000</nm:col>
<nm:col nm:cname='THETA3'>0.0000000000000000</nm:col>
<nm:col nm:cname='THETA4'>0.0000000000000000</nm:col>
<nm:col nm:cname='THETA5'>0.0000000000000000</nm:col>
<nm:col nm:cname='THETA6'>0.0000000000000000</nm:col>
<nm:col nm:cname='THETA7'>0.0000000000000000</nm:col>
<nm:col nm:cname='THETA8'>0.0000000000000000</nm:col>
<nm:col nm:cname='THETA9'>0.0000000000000000</nm:col>
<nm:col nm:cname='THETA10'>0.0000000000000000</nm:col>
<nm:col nm:cname='THETA11'>0.0000000000000000</nm:col>
<nm:col nm:cname='OMEGA(1,1)'>0.0000000000000000</nm:col>
<nm:col nm:cname='OMEGA(1,2)'>0.0000000000000000</nm:col>
</nm:row>
<nm:row nm:rname='OMEGA(1,3)'>
<nm:col nm:cname='THETA1'>0.0000000000000000</nm:col>
<nm:col nm:cname='THETA2'>0.0000000000000000</nm:col>
<nm:col nm:cname='THETA3'>0.0000000000000000</nm:col>
<nm:col nm:cname='THETA4'>0.0000000000000000</nm:col>
<nm:col nm:cname='THETA5'>0.0000000000000000</nm:col>
<nm:col nm:cname='THETA6'>0.0000000000000000</nm:col>
<nm:col nm:cname='THETA7'>0.0000000000000000</nm:col>
<nm:col nm:cname='THETA8'>0.0000000000000000</nm:col>
<nm:col nm:cname='THETA9'>0.0000000000000000</nm:col>
<nm:col nm:cname='THETA10'>0.0000000000000000</nm:col>
<nm:col nm:cname='THETA11'>0.0000000000000000</nm:col>
<nm:col nm:cname='OMEGA(1,1)'>0.0000000000000000</nm:col>
<nm:col nm:cname='OMEGA(1,2)'>0.0000000000000000</nm:col>
<nm:col nm:cname='OMEGA(1,3)'>0.0000000000000000</nm:col>
</nm:row>
<nm:row nm:rname='OMEGA(1,4)'>
<nm:col nm:cname='THETA1'>0.0000000000000000</nm:col>
<nm:col nm:cname='THETA2'>0.0000000000000000</nm:col>
<nm:col nm:cname='THETA3'>0.0000000000000000</nm:col>
<nm:col nm:cname='THETA4'>0.0000000000000000</nm:col>
<nm:col nm:cname='THETA5'>0.0000000000000000</nm:col>
<nm:col nm:cname='THETA6'>0.0000000000000000</nm:col>
<nm:col nm:cname='THETA7'>0.0000000000000000</nm:col>
<nm:col nm:cname='THETA8'>0.0000000000000000</nm:col>
<nm:col nm:cname='THETA9'>0.0000000000000000</nm:col>
<nm:col nm:cname='THETA10'>0.0000000000000000</nm:col>
<nm:col nm:cname='THETA11'>0.0000000000000000</nm:col>
<nm:col nm:cname='OMEGA(1,1)'>0.0000000000000000</nm:col>
<nm:col nm:cname='OMEGA(1,2)'>0.0000000000000000</nm:col>
<nm:col nm:cname='OMEGA(1,3)'>0.0000000000000000</nm:col>
<nm:col nm:cname='OMEGA(1,4)'>0.0000000000000000</nm:col>
</nm:row>
<nm:row nm:rname='OMEGA(1,5)'>
<nm:col nm:cname='THETA1'>0.0000000000000000</nm:col>
<nm:col nm:cname='THETA2'>0.0000000000000000</nm:col>
<nm:col nm:cname='THETA3'>0.0000000000000000</nm:col>
<nm:col nm:cname='THETA4'>0.0000000000000000</nm:col>
<nm:col nm:cname='THETA5'>0.0000000000000000</nm:col>
<nm:col nm:cname='THETA6'>0.0000000000000000</nm:col>
<nm:col nm:cname='THETA7'>0.0000000000000000</nm:col>
<nm:col nm:cname='THETA8'>0.0000000000000000</nm:col>
<nm:col nm:cname='THETA9'>0.0000000000000000</nm:col>
<nm:col nm:cname='THETA10'>0.0000000000000000</nm:col>
<nm:col nm:cname='THETA11'>0.0000000000000000</nm:col>
<nm:col nm:cname='OMEGA(1,1)'>0.0000000000000000</nm:col>
<nm:col nm:cname='OMEGA(1,2)'>0.0000000000000000</nm:col>
<nm:col nm:cname='OMEGA(1,3)'>0.0000000000000000</nm:col>
<nm:col nm:cname='OMEGA(1,4)'>0.0000000000000000</nm:col>
<nm:col nm:cname='OMEGA(1,5)'>0.0000000000000000</nm:col>
</nm:row>
<nm:row nm:rname='OMEGA(2,2)'>
<nm:col nm:cname='THETA1'>0.0000000000000000</nm:col>
<nm:col nm:cname='THETA2'>0.0000000000000000</nm:col>
<nm:col nm:cname='THETA3'>0.0000000000000000</nm:col>
<nm:col nm:cname='THETA4'>0.0000000000000000</nm:col>
<nm:col nm:cname='THETA5'>0.0000000000000000</nm:col>
<nm:col nm:cname='THETA6'>0.0000000000000000</nm:col>
<nm:col nm:cname='THETA7'>0.0000000000000000</nm:col>
<nm:col nm:cname='THETA8'>0.0000000000000000</nm:col>
<nm:col nm:cname='THETA9'>0.0000000000000000</nm:col>
<nm:col nm:cname='THETA10'>0.0000000000000000</nm:col>
<nm:col nm:cname='THETA11'>0.0000000000000000</nm:col>
<nm:col nm:cname='OMEGA(1,1)'>0.0000000000000000</nm:col>
<nm:col nm:cname='OMEGA(1,2)'>0.0000000000000000</nm:col>
<nm:col nm:cname='OMEGA(1,3)'>0.0000000000000000</nm:col>
<nm:col nm:cname='OMEGA(1,4)'>0.0000000000000000</nm:col>
<nm:col nm:cname='OMEGA(1,5)'>0.0000000000000000</nm:col>
<nm:col nm:cname='OMEGA(2,2)'>0.0000000000000000</nm:col>
</nm:row>
<nm:row nm:rname='OMEGA(2,3)'>
<nm:col nm:cname='THETA1'>0.0000000000000000</nm:col>
<nm:col nm:cname='THETA2'>0.0000000000000000</nm:col>
<nm:col nm:cname='THETA3'>0.0000000000000000</nm:col>
<nm:col nm:cname='THETA4'>0.0000000000000000</nm:col>
<nm:col nm:cname='THETA5'>0.0000000000000000</nm:col>
<nm:col nm:cname='THETA6'>0.0000000000000000</nm:col>
<nm:col nm:cname='THETA7'>0.0000000000000000</nm:col>
<nm:col nm:cname='THETA8'>0.0000000000000000</nm:col>
<nm:col nm:cname='THETA9'>0.0000000000000000</nm:col>
<nm:col nm:cname='THETA10'>0.0000000000000000</nm:col>
<nm:col nm:cname='THETA11'>0.0000000000000000</nm:col>
<nm:col nm:cname='OMEGA(1,1)'>0.0000000000000000</nm:col>
<nm:col nm:cname='OMEGA(1,2)'>0.0000000000000000</nm:col>
<nm:col nm:cname='OMEGA(1,3)'>0.0000000000000000</nm:col>
<nm:col nm:cname='OMEGA(1,4)'>0.0000000000000000</nm:col>
<nm:col nm:cname='OMEGA(1,5)'>0.0000000000000000</nm:col>
<nm:col nm:cname='OMEGA(2,2)'>0.0000000000000000</nm:col>
<nm:col nm:cname='OMEGA(2,3)'>0.0000000000000000</nm:col>
</nm:row>
<nm:row nm:rname='OMEGA(2,4)'>
<nm:col nm:cname='THETA1'>0.0000000000000000</nm:col>
<nm:col nm:cname='THETA2'>0.0000000000000000</nm:col>
<nm:col nm:cname='THETA3'>0.0000000000000000</nm:col>
<nm:col nm:cname='THETA4'>0.0000000000000000</nm:col>
<nm:col nm:cname='THETA5'>0.0000000000000000</nm:col>
<nm:col nm:cname='THETA6'>0.0000000000000000</nm:col>
<nm:col nm:cname='THETA7'>0.0000000000000000</nm:col>
<nm:col nm:cname='THETA8'>0.0000000000000000</nm:col>
<nm:col nm:cname='THETA9'>0.0000000000000000</nm:col>
<nm:col nm:cname='THETA10'>0.0000000000000000</nm:col>
<nm:col nm:cname='THETA11'>0.0000000000000000</nm:col>
<nm:col nm:cname='OMEGA(1,1)'>0.0000000000000000</nm:col>
<nm:col nm:cname='OMEGA(1,2)'>0.0000000000000000</nm:col>
<nm:col nm:cname='OMEGA(1,3)'>0.0000000000000000</nm:col>
<nm:col nm:cname='OMEGA(1,4)'>0.0000000000000000</nm:col>
<nm:col nm:cname='OMEGA(1,5)'>0.0000000000000000</nm:col>
<nm:col nm:cname='OMEGA(2,2)'>0.0000000000000000</nm:col>
<nm:col nm:cname='OMEGA(2,3)'>0.0000000000000000</nm:col>
<nm:col nm:cname='OMEGA(2,4)'>0.0000000000000000</nm:col>
</nm:row>
<nm:row nm:rname='OMEGA(2,5)'>
<nm:col nm:cname='THETA1'>0.0000000000000000</nm:col>
<nm:col nm:cname='THETA2'>0.0000000000000000</nm:col>
<nm:col nm:cname='THETA3'>0.0000000000000000</nm:col>
<nm:col nm:cname='THETA4'>0.0000000000000000</nm:col>
<nm:col nm:cname='THETA5'>0.0000000000000000</nm:col>
<nm:col nm:cname='THETA6'>0.0000000000000000</nm:col>
<nm:col nm:cname='THETA7'>0.0000000000000000</nm:col>
<nm:col nm:cname='THETA8'>0.0000000000000000</nm:col>
<nm:col nm:cname='THETA9'>0.0000000000000000</nm:col>
<nm:col nm:cname='THETA10'>0.0000000000000000</nm:col>
<nm:col nm:cname='THETA11'>0.0000000000000000</nm:col>
<nm:col nm:cname='OMEGA(1,1)'>0.0000000000000000</nm:col>
<nm:col nm:cname='OMEGA(1,2)'>0.0000000000000000</nm:col>
<nm:col nm:cname='OMEGA(1,3)'>0.0000000000000000</nm:col>
<nm:col nm:cname='OMEGA(1,4)'>0.0000000000000000</nm:col>
<nm:col nm:cname='OMEGA(1,5)'>0.0000000000000000</nm:col>
<nm:col nm:cname='OMEGA(2,2)'>0.0000000000000000</nm:col>
<nm:col nm:cname='OMEGA(2,3)'>0.0000000000000000</nm:col>
<nm:col nm:cname='OMEGA(2,4)'>0.0000000000000000</nm:col>
<nm:col nm:cname='OMEGA(2,5)'>0.0000000000000000</nm:col>
</nm:row>
<nm:row nm:rname='OMEGA(3,3)'>
<nm:col nm:cname='THETA1'>0.0000000000000000</nm:col>
<nm:col nm:cname='THETA2'>0.0000000000000000</nm:col>
<nm:col nm:cname='THETA3'>0.0000000000000000</nm:col>
<nm:col nm:cname='THETA4'>0.0000000000000000</nm:col>
<nm:col nm:cname='THETA5'>0.0000000000000000</nm:col>
<nm:col nm:cname='THETA6'>0.0000000000000000</nm:col>
<nm:col nm:cname='THETA7'>0.0000000000000000</nm:col>
<nm:col nm:cname='THETA8'>0.0000000000000000</nm:col>
<nm:col nm:cname='THETA9'>0.0000000000000000</nm:col>
<nm:col nm:cname='THETA10'>0.0000000000000000</nm:col>
<nm:col nm:cname='THETA11'>0.0000000000000000</nm:col>
<nm:col nm:cname='OMEGA(1,1)'>0.0000000000000000</nm:col>
<nm:col nm:cname='OMEGA(1,2)'>0.0000000000000000</nm:col>
<nm:col nm:cname='OMEGA(1,3)'>0.0000000000000000</nm:col>
<nm:col nm:cname='OMEGA(1,4)'>0.0000000000000000</nm:col>
<nm:col nm:cname='OMEGA(1,5)'>0.0000000000000000</nm:col>
<nm:col nm:cname='OMEGA(2,2)'>0.0000000000000000</nm:col>
<nm:col nm:cname='OMEGA(2,3)'>0.0000000000000000</nm:col>
<nm:col nm:cname='OMEGA(2,4)'>0.0000000000000000</nm:col>
<nm:col nm:cname='OMEGA(2,5)'>0.0000000000000000</nm:col>
<nm:col nm:cname='OMEGA(3,3)'>0.0000000000000000</nm:col>
</nm:row>
<nm:row nm:rname='OMEGA(3,4)'>
<nm:col nm:cname='THETA1'>0.0000000000000000</nm:col>
<nm:col nm:cname='THETA2'>0.0000000000000000</nm:col>
<nm:col nm:cname='THETA3'>0.0000000000000000</nm:col>
<nm:col nm:cname='THETA4'>0.0000000000000000</nm:col>
<nm:col nm:cname='THETA5'>0.0000000000000000</nm:col>
<nm:col nm:cname='THETA6'>0.0000000000000000</nm:col>
<nm:col nm:cname='THETA7'>0.0000000000000000</nm:col>
<nm:col nm:cname='THETA8'>0.0000000000000000</nm:col>
<nm:col nm:cname='THETA9'>0.0000000000000000</nm:col>
<nm:col nm:cname='THETA10'>0.0000000000000000</nm:col>
<nm:col nm:cname='THETA11'>0.0000000000000000</nm:col>
<nm:col nm:cname='OMEGA(1,1)'>0.0000000000000000</nm:col>
<nm:col nm:cname='OMEGA(1,2)'>0.0000000000000000</nm:col>
<nm:col nm:cname='OMEGA(1,3)'>0.0000000000000000</nm:col>
<nm:col nm:cname='OMEGA(1,4)'>0.0000000000000000</nm:col>
<nm:col nm:cname='OMEGA(1,5)'>0.0000000000000000</nm:col>
<nm:col nm:cname='OMEGA(2,2)'>0.0000000000000000</nm:col>
<nm:col nm:cname='OMEGA(2,3)'>0.0000000000000000</nm:col>
<nm:col nm:cname='OMEGA(2,4)'>0.0000000000000000</nm:col>
<nm:col nm:cname='OMEGA(2,5)'>0.0000000000000000</nm:col>
<nm:col nm:cname='OMEGA(3,3)'>0.0000000000000000</nm:col>
<nm:col nm:cname='OMEGA(3,4)'>0.0000000000000000</nm:col>
</nm:row>
<nm:row nm:rname='OMEGA(3,5)'>
<nm:col nm:cname='THETA1'>0.0000000000000000</nm:col>
<nm:col nm:cname='THETA2'>0.0000000000000000</nm:col>
<nm:col nm:cname='THETA3'>0.0000000000000000</nm:col>
<nm:col nm:cname='THETA4'>0.0000000000000000</nm:col>
<nm:col nm:cname='THETA5'>0.0000000000000000</nm:col>
<nm:col nm:cname='THETA6'>0.0000000000000000</nm:col>
<nm:col nm:cname='THETA7'>0.0000000000000000</nm:col>
<nm:col nm:cname='THETA8'>0.0000000000000000</nm:col>
<nm:col nm:cname='THETA9'>0.0000000000000000</nm:col>
<nm:col nm:cname='THETA10'>0.0000000000000000</nm:col>
<nm:col nm:cname='THETA11'>0.0000000000000000</nm:col>
<nm:col nm:cname='OMEGA(1,1)'>0.0000000000000000</nm:col>
<nm:col nm:cname='OMEGA(1,2)'>0.0000000000000000</nm:col>
<nm:col nm:cname='OMEGA(1,3)'>0.0000000000000000</nm:col>
<nm:col nm:cname='OMEGA(1,4)'>0.0000000000000000</nm:col>
<nm:col nm:cname='OMEGA(1,5)'>0.0000000000000000</nm:col>
<nm:col nm:cname='OMEGA(2,2)'>0.0000000000000000</nm:col>
<nm:col nm:cname='OMEGA(2,3)'>0.0000000000000000</nm:col>
<nm:col nm:cname='OMEGA(2,4)'>0.0000000000000000</nm:col>
<nm:col nm:cname='OMEGA(2,5)'>0.0000000000000000</nm:col>
<nm:col nm:cname='OMEGA(3,3)'>0.0000000000000000</nm:col>
<nm:col nm:cname='OMEGA(3,4)'>0.0000000000000000</nm:col>
<nm:col nm:cname='OMEGA(3,5)'>0.0000000000000000</nm:col>
</nm:row>
<nm:row nm:rname='OMEGA(4,4)'>
<nm:col nm:cname='THETA1'>0.0000000000000000</nm:col>
<nm:col nm:cname='THETA2'>0.0000000000000000</nm:col>
<nm:col nm:cname='THETA3'>0.0000000000000000</nm:col>
<nm:col nm:cname='THETA4'>0.0000000000000000</nm:col>
<nm:col nm:cname='THETA5'>0.0000000000000000</nm:col>
<nm:col nm:cname='THETA6'>0.0000000000000000</nm:col>
<nm:col nm:cname='THETA7'>0.0000000000000000</nm:col>
<nm:col nm:cname='THETA8'>0.0000000000000000</nm:col>
<nm:col nm:cname='THETA9'>0.0000000000000000</nm:col>
<nm:col nm:cname='THETA10'>0.0000000000000000</nm:col>
<nm:col nm:cname='THETA11'>0.0000000000000000</nm:col>
<nm:col nm:cname='OMEGA(1,1)'>0.0000000000000000</nm:col>
<nm:col nm:cname='OMEGA(1,2)'>0.0000000000000000</nm:col>
<nm:col nm:cname='OMEGA(1,3)'>0.0000000000000000</nm:col>
<nm:col nm:cname='OMEGA(1,4)'>0.0000000000000000</nm:col>
<nm:col nm:cname='OMEGA(1,5)'>0.0000000000000000</nm:col>
<nm:col nm:cname='OMEGA(2,2)'>0.0000000000000000</nm:col>
<nm:col nm:cname='OMEGA(2,3)'>0.0000000000000000</nm:col>
<nm:col nm:cname='OMEGA(2,4)'>0.0000000000000000</nm:col>
<nm:col nm:cname='OMEGA(2,5)'>0.0000000000000000</nm:col>
<nm:col nm:cname='OMEGA(3,3)'>0.0000000000000000</nm:col>
<nm:col nm:cname='OMEGA(3,4)'>0.0000000000000000</nm:col>
<nm:col nm:cname='OMEGA(3,5)'>0.0000000000000000</nm:col>
<nm:col nm:cname='OMEGA(4,4)'>0.0000000000000000</nm:col>
</nm:row>
<nm:row nm:rname='OMEGA(4,5)'>
<nm:col nm:cname='THETA1'>0.0000000000000000</nm:col>
<nm:col nm:cname='THETA2'>0.0000000000000000</nm:col>
<nm:col nm:cname='THETA3'>0.0000000000000000</nm:col>
<nm:col nm:cname='THETA4'>0.0000000000000000</nm:col>
<nm:col nm:cname='THETA5'>0.0000000000000000</nm:col>
<nm:col nm:cname='THETA6'>0.0000000000000000</nm:col>
<nm:col nm:cname='THETA7'>0.0000000000000000</nm:col>
<nm:col nm:cname='THETA8'>0.0000000000000000</nm:col>
<nm:col nm:cname='THETA9'>0.0000000000000000</nm:col>
<nm:col nm:cname='THETA10'>0.0000000000000000</nm:col>
<nm:col nm:cname='THETA11'>0.0000000000000000</nm:col>
<nm:col nm:cname='OMEGA(1,1)'>0.0000000000000000</nm:col>
<nm:col nm:cname='OMEGA(1,2)'>0.0000000000000000</nm:col>
<nm:col nm:cname='OMEGA(1,3)'>0.0000000000000000</nm:col>
<nm:col nm:cname='OMEGA(1,4)'>0.0000000000000000</nm:col>
<nm:col nm:cname='OMEGA(1,5)'>0.0000000000000000</nm:col>
<nm:col nm:cname='OMEGA(2,2)'>0.0000000000000000</nm:col>
<nm:col nm:cname='OMEGA(2,3)'>0.0000000000000000</nm:col>
<nm:col nm:cname='OMEGA(2,4)'>0.0000000000000000</nm:col>
<nm:col nm:cname='OMEGA(2,5)'>0.0000000000000000</nm:col>
<nm:col nm:cname='OMEGA(3,3)'>0.0000000000000000</nm:col>
<nm:col nm:cname='OMEGA(3,4)'>0.0000000000000000</nm:col>
<nm:col nm:cname='OMEGA(3,5)'>0.0000000000000000</nm:col>
<nm:col nm:cname='OMEGA(4,4)'>0.0000000000000000</nm:col>
<nm:col nm:cname='OMEGA(4,5)'>0.0000000000000000</nm:col>
</nm:row>
<nm:row nm:rname='OMEGA(5,5)'>
<nm:col nm:cname='THETA1'>0.0000000000000000</nm:col>
<nm:col nm:cname='THETA2'>0.0000000000000000</nm:col>
<nm:col nm:cname='THETA3'>0.0000000000000000</nm:col>
<nm:col nm:cname='THETA4'>0.0000000000000000</nm:col>
<nm:col nm:cname='THETA5'>0.0000000000000000</nm:col>
<nm:col nm:cname='THETA6'>0.0000000000000000</nm:col>
<nm:col nm:cname='THETA7'>0.0000000000000000</nm:col>
<nm:col nm:cname='THETA8'>0.0000000000000000</nm:col>
<nm:col nm:cname='THETA9'>0.0000000000000000</nm:col>
<nm:col nm:cname='THETA10'>0.0000000000000000</nm:col>
<nm:col nm:cname='THETA11'>0.0000000000000000</nm:col>
<nm:col nm:cname='OMEGA(1,1)'>0.0000000000000000</nm:col>
<nm:col nm:cname='OMEGA(1,2)'>0.0000000000000000</nm:col>
<nm:col nm:cname='OMEGA(1,3)'>0.0000000000000000</nm:col>
<nm:col nm:cname='OMEGA(1,4)'>0.0000000000000000</nm:col>
<nm:col nm:cname='OMEGA(1,5)'>0.0000000000000000</nm:col>
<nm:col nm:cname='OMEGA(2,2)'>0.0000000000000000</nm:col>
<nm:col nm:cname='OMEGA(2,3)'>0.0000000000000000</nm:col>
<nm:col nm:cname='OMEGA(2,4)'>0.0000000000000000</nm:col>
<nm:col nm:cname='OMEGA(2,5)'>0.0000000000000000</nm:col>
<nm:col nm:cname='OMEGA(3,3)'>0.0000000000000000</nm:col>
<nm:col nm:cname='OMEGA(3,4)'>0.0000000000000000</nm:col>
<nm:col nm:cname='OMEGA(3,5)'>0.0000000000000000</nm:col>
<nm:col nm:cname='OMEGA(4,4)'>0.0000000000000000</nm:col>
<nm:col nm:cname='OMEGA(4,5)'>0.0000000000000000</nm:col>
<nm:col nm:cname='OMEGA(5,5)'>0.0000000000000000</nm:col>
</nm:row>
<nm:row nm:rname='SIGMA(1,1)'>
<nm:col nm:cname='THETA1'>0.0000000000000000</nm:col>
<nm:col nm:cname='THETA2'>0.0000000000000000</nm:col>
<nm:col nm:cname='THETA3'>0.0000000000000000</nm:col>
<nm:col nm:cname='THETA4'>0.0000000000000000</nm:col>
<nm:col nm:cname='THETA5'>0.0000000000000000</nm:col>
<nm:col nm:cname='THETA6'>0.0000000000000000</nm:col>
<nm:col nm:cname='THETA7'>0.0000000000000000</nm:col>
<nm:col nm:cname='THETA8'>0.0000000000000000</nm:col>
<nm:col nm:cname='THETA9'>0.0000000000000000</nm:col>
<nm:col nm:cname='THETA10'>0.0000000000000000</nm:col>
<nm:col nm:cname='THETA11'>0.0000000000000000</nm:col>
<nm:col nm:cname='OMEGA(1,1)'>0.0000000000000000</nm:col>
<nm:col nm:cname='OMEGA(1,2)'>0.0000000000000000</nm:col>
<nm:col nm:cname='OMEGA(1,3)'>0.0000000000000000</nm:col>
<nm:col nm:cname='OMEGA(1,4)'>0.0000000000000000</nm:col>
<nm:col nm:cname='OMEGA(1,5)'>0.0000000000000000</nm:col>
<nm:col nm:cname='OMEGA(2,2)'>0.0000000000000000</nm:col>
<nm:col nm:cname='OMEGA(2,3)'>0.0000000000000000</nm:col>
<nm:col nm:cname='OMEGA(2,4)'>0.0000000000000000</nm:col>
<nm:col nm:cname='OMEGA(2,5)'>0.0000000000000000</nm:col>
<nm:col nm:cname='OMEGA(3,3)'>0.0000000000000000</nm:col>
<nm:col nm:cname='OMEGA(3,4)'>0.0000000000000000</nm:col>
<nm:col nm:cname='OMEGA(3,5)'>0.0000000000000000</nm:col>
<nm:col nm:cname='OMEGA(4,4)'>0.0000000000000000</nm:col>
<nm:col nm:cname='OMEGA(4,5)'>0.0000000000000000</nm:col>
<nm:col nm:cname='OMEGA(5,5)'>0.0000000000000000</nm:col>
<nm:col nm:cname='SIGMA(1,1)'>0.0000000000000000</nm:col>
</nm:row>
</nm:covariance>
<nm:correlation>
<nm:row nm:rname='THETA1'>
<nm:col nm:cname='THETA1'>2.9663721425085367E-002</nm:col>
</nm:row>
<nm:row nm:rname='THETA2'>
<nm:col nm:cname='THETA1'>-4.4236676446306668E-002</nm:col>
<nm:col nm:cname='THETA2'>0.13848779278471979</nm:col>
</nm:row>
<nm:row nm:rname='THETA3'>
<nm:col nm:cname='THETA1'>-9.3825848557289121E-002</nm:col>
<nm:col nm:cname='THETA2'>0.89806459778268333</nm:col>
<nm:col nm:cname='THETA3'>0.13374270858330436</nm:col>
</nm:row>
<nm:row nm:rname='THETA4'>
<nm:col nm:cname='THETA1'>6.0942906074983823E-002</nm:col>
<nm:col nm:cname='THETA2'>-0.81585249069693877</nm:col>
<nm:col nm:cname='THETA3'>-0.72659740555117980</nm:col>
<nm:col nm:cname='THETA4'>6.2031574325016839E-002</nm:col>
</nm:row>
<nm:row nm:rname='THETA5'>
<nm:col nm:cname='THETA1'>-9.4203778455783579E-002</nm:col>
<nm:col nm:cname='THETA2'>0.94705316612927770</nm:col>
<nm:col nm:cname='THETA3'>0.93614681873042804</nm:col>
<nm:col nm:cname='THETA4'>-0.79708542224507728</nm:col>
<nm:col nm:cname='THETA5'>0.13400739715566240</nm:col>
</nm:row>
<nm:row nm:rname='THETA6'>
<nm:col nm:cname='THETA1'>-0.33522910011604662</nm:col>
<nm:col nm:cname='THETA2'>-3.8307028549252838E-003</nm:col>
<nm:col nm:cname='THETA3'>-6.6238209367179496E-003</nm:col>
<nm:col nm:cname='THETA4'>-2.1412538844816840E-002</nm:col>
<nm:col nm:cname='THETA5'>6.2594513418517163E-003</nm:col>
<nm:col nm:cname='THETA6'>7.7370772724944664E-002</nm:col>
</nm:row>
<nm:row nm:rname='THETA7'>
<nm:col nm:cname='THETA1'>7.6775680499161295E-002</nm:col>
<nm:col nm:cname='THETA2'>-0.73151497624663619</nm:col>
<nm:col nm:cname='THETA3'>-0.70462564019028306</nm:col>
<nm:col nm:cname='THETA4'>0.50224144386419334</nm:col>
<nm:col nm:cname='THETA5'>-0.74935190220292536</nm:col>
<nm:col nm:cname='THETA6'>-5.7441392923905557E-002</nm:col>
<nm:col nm:cname='THETA7'>0.17370760952290559</nm:col>
</nm:row>
<nm:row nm:rname='THETA8'>
<nm:col nm:cname='THETA1'>-0.10763031664671453</nm:col>
<nm:col nm:cname='THETA2'>0.81481482085186341</nm:col>
<nm:col nm:cname='THETA3'>0.84884399663478638</nm:col>
<nm:col nm:cname='THETA4'>-0.63005591249447335</nm:col>
<nm:col nm:cname='THETA5'>0.84707728692036988</nm:col>
<nm:col nm:cname='THETA6'>-4.2307920878367579E-002</nm:col>
<nm:col nm:cname='THETA7'>-0.63821559290834073</nm:col>
<nm:col nm:cname='THETA8'>0.26664197990467470</nm:col>
</nm:row>
<nm:row nm:rname='THETA9'>
<nm:col nm:cname='THETA1'>-0.10239211614736964</nm:col>
<nm:col nm:cname='THETA2'>0.14169388252925072</nm:col>
<nm:col nm:cname='THETA3'>0.20052910475517532</nm:col>
<nm:col nm:cname='THETA4'>3.5915347154615695E-002</nm:col>
<nm:col nm:cname='THETA5'>0.18309501941112585</nm:col>
<nm:col nm:cname='THETA6'>-4.4002218239918622E-002</nm:col>
<nm:col nm:cname='THETA7'>4.6617516742002013E-002</nm:col>
<nm:col nm:cname='THETA8'>0.28502924580000305</nm:col>
<nm:col nm:cname='THETA9'>0.13565709222120861</nm:col>
</nm:row>
<nm:row nm:rname='THETA10'>
<nm:col nm:cname='THETA1'>-0.10239505799023924</nm:col>
<nm:col nm:cname='THETA2'>0.34811130060875334</nm:col>
<nm:col nm:cname='THETA3'>0.33868268243848698</nm:col>
<nm:col nm:cname='THETA4'>-0.25732377427719583</nm:col>
<nm:col nm:cname='THETA5'>0.35175761777350656</nm:col>
<nm:col nm:cname='THETA6'>-2.3924776175729572E-002</nm:col>
<nm:col nm:cname='THETA7'>-0.11043556964697294</nm:col>
<nm:col nm:cname='THETA8'>0.43215246385679812</nm:col>
<nm:col nm:cname='THETA9'>7.7636708960953066E-002</nm:col>
<nm:col nm:cname='THETA10'>0.10666655305111510</nm:col>
</nm:row>
<nm:row nm:rname='THETA11'>
<nm:col nm:cname='THETA1'>0.38723997702876628</nm:col>
<nm:col nm:cname='THETA2'>-0.46547078363910138</nm:col>
<nm:col nm:cname='THETA3'>-0.52473757560739154</nm:col>
<nm:col nm:cname='THETA4'>0.36769935317094027</nm:col>
<nm:col nm:cname='THETA5'>-0.49136958084851734</nm:col>
<nm:col nm:cname='THETA6'>2.4871902752071195E-002</nm:col>
<nm:col nm:cname='THETA7'>0.38317838209217903</nm:col>
<nm:col nm:cname='THETA8'>-0.55520366033319080</nm:col>
<nm:col nm:cname='THETA9'>-0.12491792748082725</nm:col>
<nm:col nm:cname='THETA10'>-0.15086843873338726</nm:col>
<nm:col nm:cname='THETA11'>5.8229388064758893E-002</nm:col>
</nm:row>
<nm:row nm:rname='OMEGA(1,1)'>
<nm:col nm:cname='THETA1'>0.0000000000000000</nm:col>
<nm:col nm:cname='THETA2'>0.0000000000000000</nm:col>
<nm:col nm:cname='THETA3'>0.0000000000000000</nm:col>
<nm:col nm:cname='THETA4'>0.0000000000000000</nm:col>
<nm:col nm:cname='THETA5'>0.0000000000000000</nm:col>
<nm:col nm:cname='THETA6'>0.0000000000000000</nm:col>
<nm:col nm:cname='THETA7'>0.0000000000000000</nm:col>
<nm:col nm:cname='THETA8'>0.0000000000000000</nm:col>
<nm:col nm:cname='THETA9'>0.0000000000000000</nm:col>
<nm:col nm:cname='THETA10'>0.0000000000000000</nm:col>
<nm:col nm:cname='THETA11'>0.0000000000000000</nm:col>
<nm:col nm:cname='OMEGA(1,1)'>0.0000000000000000</nm:col>
</nm:row>
<nm:row nm:rname='OMEGA(1,2)'>
<nm:col nm:cname='THETA1'>0.0000000000000000</nm:col>
<nm:col nm:cname='THETA2'>0.0000000000000000</nm:col>
<nm:col nm:cname='THETA3'>0.0000000000000000</nm:col>
<nm:col nm:cname='THETA4'>0.0000000000000000</nm:col>
<nm:col nm:cname='THETA5'>0.0000000000000000</nm:col>
<nm:col nm:cname='THETA6'>0.0000000000000000</nm:col>
<nm:col nm:cname='THETA7'>0.0000000000000000</nm:col>
<nm:col nm:cname='THETA8'>0.0000000000000000</nm:col>
<nm:col nm:cname='THETA9'>0.0000000000000000</nm:col>
<nm:col nm:cname='THETA10'>0.0000000000000000</nm:col>
<nm:col nm:cname='THETA11'>0.0000000000000000</nm:col>
<nm:col nm:cname='OMEGA(1,1)'>0.0000000000000000</nm:col>
<nm:col nm:cname='OMEGA(1,2)'>0.0000000000000000</nm:col>
</nm:row>
<nm:row nm:rname='OMEGA(1,3)'>
<nm:col nm:cname='THETA1'>0.0000000000000000</nm:col>
<nm:col nm:cname='THETA2'>0.0000000000000000</nm:col>
<nm:col nm:cname='THETA3'>0.0000000000000000</nm:col>
<nm:col nm:cname='THETA4'>0.0000000000000000</nm:col>
<nm:col nm:cname='THETA5'>0.0000000000000000</nm:col>
<nm:col nm:cname='THETA6'>0.0000000000000000</nm:col>
<nm:col nm:cname='THETA7'>0.0000000000000000</nm:col>
<nm:col nm:cname='THETA8'>0.0000000000000000</nm:col>
<nm:col nm:cname='THETA9'>0.0000000000000000</nm:col>
<nm:col nm:cname='THETA10'>0.0000000000000000</nm:col>
<nm:col nm:cname='THETA11'>0.0000000000000000</nm:col>
<nm:col nm:cname='OMEGA(1,1)'>0.0000000000000000</nm:col>
<nm:col nm:cname='OMEGA(1,2)'>0.0000000000000000</nm:col>
<nm:col nm:cname='OMEGA(1,3)'>0.0000000000000000</nm:col>
</nm:row>
<nm:row nm:rname='OMEGA(1,4)'>
<nm:col nm:cname='THETA1'>0.0000000000000000</nm:col>
<nm:col nm:cname='THETA2'>0.0000000000000000</nm:col>
<nm:col nm:cname='THETA3'>0.0000000000000000</nm:col>
<nm:col nm:cname='THETA4'>0.0000000000000000</nm:col>
<nm:col nm:cname='THETA5'>0.0000000000000000</nm:col>
<nm:col nm:cname='THETA6'>0.0000000000000000</nm:col>
<nm:col nm:cname='THETA7'>0.0000000000000000</nm:col>
<nm:col nm:cname='THETA8'>0.0000000000000000</nm:col>
<nm:col nm:cname='THETA9'>0.0000000000000000</nm:col>
<nm:col nm:cname='THETA10'>0.0000000000000000</nm:col>
<nm:col nm:cname='THETA11'>0.0000000000000000</nm:col>
<nm:col nm:cname='OMEGA(1,1)'>0.0000000000000000</nm:col>
<nm:col nm:cname='OMEGA(1,2)'>0.0000000000000000</nm:col>
<nm:col nm:cname='OMEGA(1,3)'>0.0000000000000000</nm:col>
<nm:col nm:cname='OMEGA(1,4)'>0.0000000000000000</nm:col>
</nm:row>
<nm:row nm:rname='OMEGA(1,5)'>
<nm:col nm:cname='THETA1'>0.0000000000000000</nm:col>
<nm:col nm:cname='THETA2'>0.0000000000000000</nm:col>
<nm:col nm:cname='THETA3'>0.0000000000000000</nm:col>
<nm:col nm:cname='THETA4'>0.0000000000000000</nm:col>
<nm:col nm:cname='THETA5'>0.0000000000000000</nm:col>
<nm:col nm:cname='THETA6'>0.0000000000000000</nm:col>
<nm:col nm:cname='THETA7'>0.0000000000000000</nm:col>
<nm:col nm:cname='THETA8'>0.0000000000000000</nm:col>
<nm:col nm:cname='THETA9'>0.0000000000000000</nm:col>
<nm:col nm:cname='THETA10'>0.0000000000000000</nm:col>
<nm:col nm:cname='THETA11'>0.0000000000000000</nm:col>
<nm:col nm:cname='OMEGA(1,1)'>0.0000000000000000</nm:col>
<nm:col nm:cname='OMEGA(1,2)'>0.0000000000000000</nm:col>
<nm:col nm:cname='OMEGA(1,3)'>0.0000000000000000</nm:col>
<nm:col nm:cname='OMEGA(1,4)'>0.0000000000000000</nm:col>
<nm:col nm:cname='OMEGA(1,5)'>0.0000000000000000</nm:col>
</nm:row>
<nm:row nm:rname='OMEGA(2,2)'>
<nm:col nm:cname='THETA1'>0.0000000000000000</nm:col>
<nm:col nm:cname='THETA2'>0.0000000000000000</nm:col>
<nm:col nm:cname='THETA3'>0.0000000000000000</nm:col>
<nm:col nm:cname='THETA4'>0.0000000000000000</nm:col>
<nm:col nm:cname='THETA5'>0.0000000000000000</nm:col>
<nm:col nm:cname='THETA6'>0.0000000000000000</nm:col>
<nm:col nm:cname='THETA7'>0.0000000000000000</nm:col>
<nm:col nm:cname='THETA8'>0.0000000000000000</nm:col>
<nm:col nm:cname='THETA9'>0.0000000000000000</nm:col>
<nm:col nm:cname='THETA10'>0.0000000000000000</nm:col>
<nm:col nm:cname='THETA11'>0.0000000000000000</nm:col>
<nm:col nm:cname='OMEGA(1,1)'>0.0000000000000000</nm:col>
<nm:col nm:cname='OMEGA(1,2)'>0.0000000000000000</nm:col>
<nm:col nm:cname='OMEGA(1,3)'>0.0000000000000000</nm:col>
<nm:col nm:cname='OMEGA(1,4)'>0.0000000000000000</nm:col>
<nm:col nm:cname='OMEGA(1,5)'>0.0000000000000000</nm:col>
<nm:col nm:cname='OMEGA(2,2)'>0.0000000000000000</nm:col>
</nm:row>
<nm:row nm:rname='OMEGA(2,3)'>
<nm:col nm:cname='THETA1'>0.0000000000000000</nm:col>
<nm:col nm:cname='THETA2'>0.0000000000000000</nm:col>
<nm:col nm:cname='THETA3'>0.0000000000000000</nm:col>
<nm:col nm:cname='THETA4'>0.0000000000000000</nm:col>
<nm:col nm:cname='THETA5'>0.0000000000000000</nm:col>
<nm:col nm:cname='THETA6'>0.0000000000000000</nm:col>
<nm:col nm:cname='THETA7'>0.0000000000000000</nm:col>
<nm:col nm:cname='THETA8'>0.0000000000000000</nm:col>
<nm:col nm:cname='THETA9'>0.0000000000000000</nm:col>
<nm:col nm:cname='THETA10'>0.0000000000000000</nm:col>
<nm:col nm:cname='THETA11'>0.0000000000000000</nm:col>
<nm:col nm:cname='OMEGA(1,1)'>0.0000000000000000</nm:col>
<nm:col nm:cname='OMEGA(1,2)'>0.0000000000000000</nm:col>
<nm:col nm:cname='OMEGA(1,3)'>0.0000000000000000</nm:col>
<nm:col nm:cname='OMEGA(1,4)'>0.0000000000000000</nm:col>
<nm:col nm:cname='OMEGA(1,5)'>0.0000000000000000</nm:col>
<nm:col nm:cname='OMEGA(2,2)'>0.0000000000000000</nm:col>
<nm:col nm:cname='OMEGA(2,3)'>0.0000000000000000</nm:col>
</nm:row>
<nm:row nm:rname='OMEGA(2,4)'>
<nm:col nm:cname='THETA1'>0.0000000000000000</nm:col>
<nm:col nm:cname='THETA2'>0.0000000000000000</nm:col>
<nm:col nm:cname='THETA3'>0.0000000000000000</nm:col>
<nm:col nm:cname='THETA4'>0.0000000000000000</nm:col>
<nm:col nm:cname='THETA5'>0.0000000000000000</nm:col>
<nm:col nm:cname='THETA6'>0.0000000000000000</nm:col>
<nm:col nm:cname='THETA7'>0.0000000000000000</nm:col>
<nm:col nm:cname='THETA8'>0.0000000000000000</nm:col>
<nm:col nm:cname='THETA9'>0.0000000000000000</nm:col>
<nm:col nm:cname='THETA10'>0.0000000000000000</nm:col>
<nm:col nm:cname='THETA11'>0.0000000000000000</nm:col>
<nm:col nm:cname='OMEGA(1,1)'>0.0000000000000000</nm:col>
<nm:col nm:cname='OMEGA(1,2)'>0.0000000000000000</nm:col>
<nm:col nm:cname='OMEGA(1,3)'>0.0000000000000000</nm:col>
<nm:col nm:cname='OMEGA(1,4)'>0.0000000000000000</nm:col>
<nm:col nm:cname='OMEGA(1,5)'>0.0000000000000000</nm:col>
<nm:col nm:cname='OMEGA(2,2)'>0.0000000000000000</nm:col>
<nm:col nm:cname='OMEGA(2,3)'>0.0000000000000000</nm:col>
<nm:col nm:cname='OMEGA(2,4)'>0.0000000000000000</nm:col>
</nm:row>
<nm:row nm:rname='OMEGA(2,5)'>
<nm:col nm:cname='THETA1'>0.0000000000000000</nm:col>
<nm:col nm:cname='THETA2'>0.0000000000000000</nm:col>
<nm:col nm:cname='THETA3'>0.0000000000000000</nm:col>
<nm:col nm:cname='THETA4'>0.0000000000000000</nm:col>
<nm:col nm:cname='THETA5'>0.0000000000000000</nm:col>
<nm:col nm:cname='THETA6'>0.0000000000000000</nm:col>
<nm:col nm:cname='THETA7'>0.0000000000000000</nm:col>
<nm:col nm:cname='THETA8'>0.0000000000000000</nm:col>
<nm:col nm:cname='THETA9'>0.0000000000000000</nm:col>
<nm:col nm:cname='THETA10'>0.0000000000000000</nm:col>
<nm:col nm:cname='THETA11'>0.0000000000000000</nm:col>
<nm:col nm:cname='OMEGA(1,1)'>0.0000000000000000</nm:col>
<nm:col nm:cname='OMEGA(1,2)'>0.0000000000000000</nm:col>
<nm:col nm:cname='OMEGA(1,3)'>0.0000000000000000</nm:col>
<nm:col nm:cname='OMEGA(1,4)'>0.0000000000000000</nm:col>
<nm:col nm:cname='OMEGA(1,5)'>0.0000000000000000</nm:col>
<nm:col nm:cname='OMEGA(2,2)'>0.0000000000000000</nm:col>
<nm:col nm:cname='OMEGA(2,3)'>0.0000000000000000</nm:col>
<nm:col nm:cname='OMEGA(2,4)'>0.0000000000000000</nm:col>
<nm:col nm:cname='OMEGA(2,5)'>0.0000000000000000</nm:col>
</nm:row>
<nm:row nm:rname='OMEGA(3,3)'>
<nm:col nm:cname='THETA1'>0.0000000000000000</nm:col>
<nm:col nm:cname='THETA2'>0.0000000000000000</nm:col>
<nm:col nm:cname='THETA3'>0.0000000000000000</nm:col>
<nm:col nm:cname='THETA4'>0.0000000000000000</nm:col>
<nm:col nm:cname='THETA5'>0.0000000000000000</nm:col>
<nm:col nm:cname='THETA6'>0.0000000000000000</nm:col>
<nm:col nm:cname='THETA7'>0.0000000000000000</nm:col>
<nm:col nm:cname='THETA8'>0.0000000000000000</nm:col>
<nm:col nm:cname='THETA9'>0.0000000000000000</nm:col>
<nm:col nm:cname='THETA10'>0.0000000000000000</nm:col>
<nm:col nm:cname='THETA11'>0.0000000000000000</nm:col>
<nm:col nm:cname='OMEGA(1,1)'>0.0000000000000000</nm:col>
<nm:col nm:cname='OMEGA(1,2)'>0.0000000000000000</nm:col>
<nm:col nm:cname='OMEGA(1,3)'>0.0000000000000000</nm:col>
<nm:col nm:cname='OMEGA(1,4)'>0.0000000000000000</nm:col>
<nm:col nm:cname='OMEGA(1,5)'>0.0000000000000000</nm:col>
<nm:col nm:cname='OMEGA(2,2)'>0.0000000000000000</nm:col>
<nm:col nm:cname='OMEGA(2,3)'>0.0000000000000000</nm:col>
<nm:col nm:cname='OMEGA(2,4)'>0.0000000000000000</nm:col>
<nm:col nm:cname='OMEGA(2,5)'>0.0000000000000000</nm:col>
<nm:col nm:cname='OMEGA(3,3)'>0.0000000000000000</nm:col>
</nm:row>
<nm:row nm:rname='OMEGA(3,4)'>
<nm:col nm:cname='THETA1'>0.0000000000000000</nm:col>
<nm:col nm:cname='THETA2'>0.0000000000000000</nm:col>
<nm:col nm:cname='THETA3'>0.0000000000000000</nm:col>
<nm:col nm:cname='THETA4'>0.0000000000000000</nm:col>
<nm:col nm:cname='THETA5'>0.0000000000000000</nm:col>
<nm:col nm:cname='THETA6'>0.0000000000000000</nm:col>
<nm:col nm:cname='THETA7'>0.0000000000000000</nm:col>
<nm:col nm:cname='THETA8'>0.0000000000000000</nm:col>
<nm:col nm:cname='THETA9'>0.0000000000000000</nm:col>
<nm:col nm:cname='THETA10'>0.0000000000000000</nm:col>
<nm:col nm:cname='THETA11'>0.0000000000000000</nm:col>
<nm:col nm:cname='OMEGA(1,1)'>0.0000000000000000</nm:col>
<nm:col nm:cname='OMEGA(1,2)'>0.0000000000000000</nm:col>
<nm:col nm:cname='OMEGA(1,3)'>0.0000000000000000</nm:col>
<nm:col nm:cname='OMEGA(1,4)'>0.0000000000000000</nm:col>
<nm:col nm:cname='OMEGA(1,5)'>0.0000000000000000</nm:col>
<nm:col nm:cname='OMEGA(2,2)'>0.0000000000000000</nm:col>
<nm:col nm:cname='OMEGA(2,3)'>0.0000000000000000</nm:col>
<nm:col nm:cname='OMEGA(2,4)'>0.0000000000000000</nm:col>
<nm:col nm:cname='OMEGA(2,5)'>0.0000000000000000</nm:col>
<nm:col nm:cname='OMEGA(3,3)'>0.0000000000000000</nm:col>
<nm:col nm:cname='OMEGA(3,4)'>0.0000000000000000</nm:col>
</nm:row>
<nm:row nm:rname='OMEGA(3,5)'>
<nm:col nm:cname='THETA1'>0.0000000000000000</nm:col>
<nm:col nm:cname='THETA2'>0.0000000000000000</nm:col>
<nm:col nm:cname='THETA3'>0.0000000000000000</nm:col>
<nm:col nm:cname='THETA4'>0.0000000000000000</nm:col>
<nm:col nm:cname='THETA5'>0.0000000000000000</nm:col>
<nm:col nm:cname='THETA6'>0.0000000000000000</nm:col>
<nm:col nm:cname='THETA7'>0.0000000000000000</nm:col>
<nm:col nm:cname='THETA8'>0.0000000000000000</nm:col>
<nm:col nm:cname='THETA9'>0.0000000000000000</nm:col>
<nm:col nm:cname='THETA10'>0.0000000000000000</nm:col>
<nm:col nm:cname='THETA11'>0.0000000000000000</nm:col>
<nm:col nm:cname='OMEGA(1,1)'>0.0000000000000000</nm:col>
<nm:col nm:cname='OMEGA(1,2)'>0.0000000000000000</nm:col>
<nm:col nm:cname='OMEGA(1,3)'>0.0000000000000000</nm:col>
<nm:col nm:cname='OMEGA(1,4)'>0.0000000000000000</nm:col>
<nm:col nm:cname='OMEGA(1,5)'>0.0000000000000000</nm:col>
<nm:col nm:cname='OMEGA(2,2)'>0.0000000000000000</nm:col>
<nm:col nm:cname='OMEGA(2,3)'>0.0000000000000000</nm:col>
<nm:col nm:cname='OMEGA(2,4)'>0.0000000000000000</nm:col>
<nm:col nm:cname='OMEGA(2,5)'>0.0000000000000000</nm:col>
<nm:col nm:cname='OMEGA(3,3)'>0.0000000000000000</nm:col>
<nm:col nm:cname='OMEGA(3,4)'>0.0000000000000000</nm:col>
<nm:col nm:cname='OMEGA(3,5)'>0.0000000000000000</nm:col>
</nm:row>
<nm:row nm:rname='OMEGA(4,4)'>
<nm:col nm:cname='THETA1'>0.0000000000000000</nm:col>
<nm:col nm:cname='THETA2'>0.0000000000000000</nm:col>
<nm:col nm:cname='THETA3'>0.0000000000000000</nm:col>
<nm:col nm:cname='THETA4'>0.0000000000000000</nm:col>
<nm:col nm:cname='THETA5'>0.0000000000000000</nm:col>
<nm:col nm:cname='THETA6'>0.0000000000000000</nm:col>
<nm:col nm:cname='THETA7'>0.0000000000000000</nm:col>
<nm:col nm:cname='THETA8'>0.0000000000000000</nm:col>
<nm:col nm:cname='THETA9'>0.0000000000000000</nm:col>
<nm:col nm:cname='THETA10'>0.0000000000000000</nm:col>
<nm:col nm:cname='THETA11'>0.0000000000000000</nm:col>
<nm:col nm:cname='OMEGA(1,1)'>0.0000000000000000</nm:col>
<nm:col nm:cname='OMEGA(1,2)'>0.0000000000000000</nm:col>
<nm:col nm:cname='OMEGA(1,3)'>0.0000000000000000</nm:col>
<nm:col nm:cname='OMEGA(1,4)'>0.0000000000000000</nm:col>
<nm:col nm:cname='OMEGA(1,5)'>0.0000000000000000</nm:col>
<nm:col nm:cname='OMEGA(2,2)'>0.0000000000000000</nm:col>
<nm:col nm:cname='OMEGA(2,3)'>0.0000000000000000</nm:col>
<nm:col nm:cname='OMEGA(2,4)'>0.0000000000000000</nm:col>
<nm:col nm:cname='OMEGA(2,5)'>0.0000000000000000</nm:col>
<nm:col nm:cname='OMEGA(3,3)'>0.0000000000000000</nm:col>
<nm:col nm:cname='OMEGA(3,4)'>0.0000000000000000</nm:col>
<nm:col nm:cname='OMEGA(3,5)'>0.0000000000000000</nm:col>
<nm:col nm:cname='OMEGA(4,4)'>0.0000000000000000</nm:col>
</nm:row>
<nm:row nm:rname='OMEGA(4,5)'>
<nm:col nm:cname='THETA1'>0.0000000000000000</nm:col>
<nm:col nm:cname='THETA2'>0.0000000000000000</nm:col>
<nm:col nm:cname='THETA3'>0.0000000000000000</nm:col>
<nm:col nm:cname='THETA4'>0.0000000000000000</nm:col>
<nm:col nm:cname='THETA5'>0.0000000000000000</nm:col>
<nm:col nm:cname='THETA6'>0.0000000000000000</nm:col>
<nm:col nm:cname='THETA7'>0.0000000000000000</nm:col>
<nm:col nm:cname='THETA8'>0.0000000000000000</nm:col>
<nm:col nm:cname='THETA9'>0.0000000000000000</nm:col>
<nm:col nm:cname='THETA10'>0.0000000000000000</nm:col>
<nm:col nm:cname='THETA11'>0.0000000000000000</nm:col>
<nm:col nm:cname='OMEGA(1,1)'>0.0000000000000000</nm:col>
<nm:col nm:cname='OMEGA(1,2)'>0.0000000000000000</nm:col>
<nm:col nm:cname='OMEGA(1,3)'>0.0000000000000000</nm:col>
<nm:col nm:cname='OMEGA(1,4)'>0.0000000000000000</nm:col>
<nm:col nm:cname='OMEGA(1,5)'>0.0000000000000000</nm:col>
<nm:col nm:cname='OMEGA(2,2)'>0.0000000000000000</nm:col>
<nm:col nm:cname='OMEGA(2,3)'>0.0000000000000000</nm:col>
<nm:col nm:cname='OMEGA(2,4)'>0.0000000000000000</nm:col>
<nm:col nm:cname='OMEGA(2,5)'>0.0000000000000000</nm:col>
<nm:col nm:cname='OMEGA(3,3)'>0.0000000000000000</nm:col>
<nm:col nm:cname='OMEGA(3,4)'>0.0000000000000000</nm:col>
<nm:col nm:cname='OMEGA(3,5)'>0.0000000000000000</nm:col>
<nm:col nm:cname='OMEGA(4,4)'>0.0000000000000000</nm:col>
<nm:col nm:cname='OMEGA(4,5)'>0.0000000000000000</nm:col>
</nm:row>
<nm:row nm:rname='OMEGA(5,5)'>
<nm:col nm:cname='THETA1'>0.0000000000000000</nm:col>
<nm:col nm:cname='THETA2'>0.0000000000000000</nm:col>
<nm:col nm:cname='THETA3'>0.0000000000000000</nm:col>
<nm:col nm:cname='THETA4'>0.0000000000000000</nm:col>
<nm:col nm:cname='THETA5'>0.0000000000000000</nm:col>
<nm:col nm:cname='THETA6'>0.0000000000000000</nm:col>
<nm:col nm:cname='THETA7'>0.0000000000000000</nm:col>
<nm:col nm:cname='THETA8'>0.0000000000000000</nm:col>
<nm:col nm:cname='THETA9'>0.0000000000000000</nm:col>
<nm:col nm:cname='THETA10'>0.0000000000000000</nm:col>
<nm:col nm:cname='THETA11'>0.0000000000000000</nm:col>
<nm:col nm:cname='OMEGA(1,1)'>0.0000000000000000</nm:col>
<nm:col nm:cname='OMEGA(1,2)'>0.0000000000000000</nm:col>
<nm:col nm:cname='OMEGA(1,3)'>0.0000000000000000</nm:col>
<nm:col nm:cname='OMEGA(1,4)'>0.0000000000000000</nm:col>
<nm:col nm:cname='OMEGA(1,5)'>0.0000000000000000</nm:col>
<nm:col nm:cname='OMEGA(2,2)'>0.0000000000000000</nm:col>
<nm:col nm:cname='OMEGA(2,3)'>0.0000000000000000</nm:col>
<nm:col nm:cname='OMEGA(2,4)'>0.0000000000000000</nm:col>
<nm:col nm:cname='OMEGA(2,5)'>0.0000000000000000</nm:col>
<nm:col nm:cname='OMEGA(3,3)'>0.0000000000000000</nm:col>
<nm:col nm:cname='OMEGA(3,4)'>0.0000000000000000</nm:col>
<nm:col nm:cname='OMEGA(3,5)'>0.0000000000000000</nm:col>
<nm:col nm:cname='OMEGA(4,4)'>0.0000000000000000</nm:col>
<nm:col nm:cname='OMEGA(4,5)'>0.0000000000000000</nm:col>
<nm:col nm:cname='OMEGA(5,5)'>0.0000000000000000</nm:col>
</nm:row>
<nm:row nm:rname='SIGMA(1,1)'>
<nm:col nm:cname='THETA1'>0.0000000000000000</nm:col>
<nm:col nm:cname='THETA2'>0.0000000000000000</nm:col>
<nm:col nm:cname='THETA3'>0.0000000000000000</nm:col>
<nm:col nm:cname='THETA4'>0.0000000000000000</nm:col>
<nm:col nm:cname='THETA5'>0.0000000000000000</nm:col>
<nm:col nm:cname='THETA6'>0.0000000000000000</nm:col>
<nm:col nm:cname='THETA7'>0.0000000000000000</nm:col>
<nm:col nm:cname='THETA8'>0.0000000000000000</nm:col>
<nm:col nm:cname='THETA9'>0.0000000000000000</nm:col>
<nm:col nm:cname='THETA10'>0.0000000000000000</nm:col>
<nm:col nm:cname='THETA11'>0.0000000000000000</nm:col>
<nm:col nm:cname='OMEGA(1,1)'>0.0000000000000000</nm:col>
<nm:col nm:cname='OMEGA(1,2)'>0.0000000000000000</nm:col>
<nm:col nm:cname='OMEGA(1,3)'>0.0000000000000000</nm:col>
<nm:col nm:cname='OMEGA(1,4)'>0.0000000000000000</nm:col>
<nm:col nm:cname='OMEGA(1,5)'>0.0000000000000000</nm:col>
<nm:col nm:cname='OMEGA(2,2)'>0.0000000000000000</nm:col>
<nm:col nm:cname='OMEGA(2,3)'>0.0000000000000000</nm:col>
<nm:col nm:cname='OMEGA(2,4)'>0.0000000000000000</nm:col>
<nm:col nm:cname='OMEGA(2,5)'>0.0000000000000000</nm:col>
<nm:col nm:cname='OMEGA(3,3)'>0.0000000000000000</nm:col>
<nm:col nm:cname='OMEGA(3,4)'>0.0000000000000000</nm:col>
<nm:col nm:cname='OMEGA(3,5)'>0.0000000000000000</nm:col>
<nm:col nm:cname='OMEGA(4,4)'>0.0000000000000000</nm:col>
<nm:col nm:cname='OMEGA(4,5)'>0.0000000000000000</nm:col>
<nm:col nm:cname='OMEGA(5,5)'>0.0000000000000000</nm:col>
<nm:col nm:cname='SIGMA(1,1)'>0.0000000000000000</nm:col>
</nm:row>
</nm:correlation>
<nm:invcovariance>
<nm:row nm:rname='THETA1'>
<nm:col nm:cname='THETA1'>1697.7480765340438</nm:col>
</nm:row>
<nm:row nm:rname='THETA2'>
<nm:col nm:cname='THETA1'>-170.43645973582062</nm:col>
<nm:col nm:cname='THETA2'>628.75602644684841</nm:col>
</nm:row>
<nm:row nm:rname='THETA3'>
<nm:col nm:cname='THETA1'>-32.647222798716719</nm:col>
<nm:col nm:cname='THETA2'>-64.138787486576064</nm:col>
<nm:col nm:cname='THETA3'>516.20581788215452</nm:col>
</nm:row>
<nm:row nm:rname='THETA4'>
<nm:col nm:cname='THETA1'>-121.47152759062303</nm:col>
<nm:col nm:cname='THETA2'>316.98713185629003</nm:col>
<nm:col nm:cname='THETA3'>-68.896909011648717</nm:col>
<nm:col nm:cname='THETA4'>1083.9162270859922</nm:col>
</nm:row>
<nm:row nm:rname='THETA5'>
<nm:col nm:cname='THETA1'>81.527143916793193</nm:col>
<nm:col nm:cname='THETA2'>-348.71510937896568</nm:col>
<nm:col nm:cname='THETA3'>-371.60457620854277</nm:col>
<nm:col nm:cname='THETA4'>339.01874711868282</nm:col>
<nm:col nm:cname='THETA5'>1047.0191843671187</nm:col>
</nm:row>
<nm:row nm:rname='THETA6'>
<nm:col nm:cname='THETA1'>218.74116170393663</nm:col>
<nm:col nm:cname='THETA2'>-5.2158729570675026</nm:col>
<nm:col nm:cname='THETA3'>-4.1991510588697301</nm:col>
<nm:col nm:cname='THETA4'>8.5524623405887592</nm:col>
<nm:col nm:cname='THETA5'>2.7140396973794032</nm:col>
<nm:col nm:cname='THETA6'>198.50150265517277</nm:col>
</nm:row>
<nm:row nm:rname='THETA7'>
<nm:col nm:cname='THETA1'>-38.595853097487641</nm:col>
<nm:col nm:cname='THETA2'>63.657206198813832</nm:col>
<nm:col nm:cname='THETA3'>-10.215432231975054</nm:col>
<nm:col nm:cname='THETA4'>149.98353599551893</nm:col>
<nm:col nm:cname='THETA5'>109.90875930318894</nm:col>
<nm:col nm:cname='THETA6'>8.4669705179547741</nm:col>
<nm:col nm:cname='THETA7'>112.56069208758214</nm:col>
</nm:row>
<nm:row nm:rname='THETA8'>
<nm:col nm:cname='THETA1'>-33.358227759208667</nm:col>
<nm:col nm:cname='THETA2'>-6.6454512805778414</nm:col>
<nm:col nm:cname='THETA3'>-43.365068819344138</nm:col>
<nm:col nm:cname='THETA4'>4.0435895343157888</nm:col>
<nm:col nm:cname='THETA5'>-33.573444823212988</nm:col>
<nm:col nm:cname='THETA6'>4.0373758364292289</nm:col>
<nm:col nm:cname='THETA7'>13.857367151262572</nm:col>
<nm:col nm:cname='THETA8'>71.038291154684700</nm:col>
</nm:row>
<nm:row nm:rname='THETA9'>
<nm:col nm:cname='THETA1'>54.899952691858005</nm:col>
<nm:col nm:cname='THETA2'>-20.642735837528086</nm:col>
<nm:col nm:cname='THETA3'>2.5989822138962446</nm:col>
<nm:col nm:cname='THETA4'>-119.02290863498980</nm:col>
<nm:col nm:cname='THETA5'>-56.661556830704122</nm:col>
<nm:col nm:cname='THETA6'>4.6355055045066802</nm:col>
<nm:col nm:cname='THETA7'>-41.400831210712489</nm:col>
<nm:col nm:cname='THETA8'>-20.735379646711355</nm:col>
<nm:col nm:cname='THETA9'>81.835937347720403</nm:col>
</nm:row>
<nm:row nm:rname='THETA10'>
<nm:col nm:cname='THETA1'>76.768071038834094</nm:col>
<nm:col nm:cname='THETA2'>-37.364476690831495</nm:col>
<nm:col nm:cname='THETA3'>13.231633398537527</nm:col>
<nm:col nm:cname='THETA4'>-67.623975465383012</nm:col>
<nm:col nm:cname='THETA5'>-35.539064205614984</nm:col>
<nm:col nm:cname='THETA6'>5.8817025232234279</nm:col>
<nm:col nm:cname='THETA7'>-40.978492549549351</nm:col>
<nm:col nm:cname='THETA8'>-31.501927062060261</nm:col>
<nm:col nm:cname='THETA9'>22.025141939596537</nm:col>
<nm:col nm:cname='THETA10'>127.73176809659118</nm:col>
</nm:row>
<nm:row nm:rname='THETA11'>
<nm:col nm:cname='THETA1'>-433.89561512424962</nm:col>
<nm:col nm:cname='THETA2'>28.051742164861494</nm:col>
<nm:col nm:cname='THETA3'>70.330654662506248</nm:col>
<nm:col nm:cname='THETA4'>35.859931304530143</nm:col>
<nm:col nm:cname='THETA5'>-36.187084164584348</nm:col>
<nm:col nm:cname='THETA6'>-57.266869484706646</nm:col>
<nm:col nm:cname='THETA7'>14.221198626376633</nm:col>
<nm:col nm:cname='THETA8'>57.300940738689071</nm:col>
<nm:col nm:cname='THETA9'>-23.644539994124578</nm:col>
<nm:col nm:cname='THETA10'>-45.991883570469710</nm:col>
<nm:col nm:cname='THETA11'>553.09887906222184</nm:col>
</nm:row>
<nm:row nm:rname='OMEGA(1,1)'>
<nm:col nm:cname='THETA1'>0.0000000000000000</nm:col>
<nm:col nm:cname='THETA2'>0.0000000000000000</nm:col>
<nm:col nm:cname='THETA3'>0.0000000000000000</nm:col>
<nm:col nm:cname='THETA4'>0.0000000000000000</nm:col>
<nm:col nm:cname='THETA5'>0.0000000000000000</nm:col>
<nm:col nm:cname='THETA6'>0.0000000000000000</nm:col>
<nm:col nm:cname='THETA7'>0.0000000000000000</nm:col>
<nm:col nm:cname='THETA8'>0.0000000000000000</nm:col>
<nm:col nm:cname='THETA9'>0.0000000000000000</nm:col>
<nm:col nm:cname='THETA10'>0.0000000000000000</nm:col>
<nm:col nm:cname='THETA11'>0.0000000000000000</nm:col>
<nm:col nm:cname='OMEGA(1,1)'>0.0000000000000000</nm:col>
</nm:row>
<nm:row nm:rname='OMEGA(1,2)'>
<nm:col nm:cname='THETA1'>0.0000000000000000</nm:col>
<nm:col nm:cname='THETA2'>0.0000000000000000</nm:col>
<nm:col nm:cname='THETA3'>0.0000000000000000</nm:col>
<nm:col nm:cname='THETA4'>0.0000000000000000</nm:col>
<nm:col nm:cname='THETA5'>0.0000000000000000</nm:col>
<nm:col nm:cname='THETA6'>0.0000000000000000</nm:col>
<nm:col nm:cname='THETA7'>0.0000000000000000</nm:col>
<nm:col nm:cname='THETA8'>0.0000000000000000</nm:col>
<nm:col nm:cname='THETA9'>0.0000000000000000</nm:col>
<nm:col nm:cname='THETA10'>0.0000000000000000</nm:col>
<nm:col nm:cname='THETA11'>0.0000000000000000</nm:col>
<nm:col nm:cname='OMEGA(1,1)'>0.0000000000000000</nm:col>
<nm:col nm:cname='OMEGA(1,2)'>0.0000000000000000</nm:col>
</nm:row>
<nm:row nm:rname='OMEGA(1,3)'>
<nm:col nm:cname='THETA1'>0.0000000000000000</nm:col>
<nm:col nm:cname='THETA2'>0.0000000000000000</nm:col>
<nm:col nm:cname='THETA3'>0.0000000000000000</nm:col>
<nm:col nm:cname='THETA4'>0.0000000000000000</nm:col>
<nm:col nm:cname='THETA5'>0.0000000000000000</nm:col>
<nm:col nm:cname='THETA6'>0.0000000000000000</nm:col>
<nm:col nm:cname='THETA7'>0.0000000000000000</nm:col>
<nm:col nm:cname='THETA8'>0.0000000000000000</nm:col>
<nm:col nm:cname='THETA9'>0.0000000000000000</nm:col>
<nm:col nm:cname='THETA10'>0.0000000000000000</nm:col>
<nm:col nm:cname='THETA11'>0.0000000000000000</nm:col>
<nm:col nm:cname='OMEGA(1,1)'>0.0000000000000000</nm:col>
<nm:col nm:cname='OMEGA(1,2)'>0.0000000000000000</nm:col>
<nm:col nm:cname='OMEGA(1,3)'>0.0000000000000000</nm:col>
</nm:row>
<nm:row nm:rname='OMEGA(1,4)'>
<nm:col nm:cname='THETA1'>0.0000000000000000</nm:col>
<nm:col nm:cname='THETA2'>0.0000000000000000</nm:col>
<nm:col nm:cname='THETA3'>0.0000000000000000</nm:col>
<nm:col nm:cname='THETA4'>0.0000000000000000</nm:col>
<nm:col nm:cname='THETA5'>0.0000000000000000</nm:col>
<nm:col nm:cname='THETA6'>0.0000000000000000</nm:col>
<nm:col nm:cname='THETA7'>0.0000000000000000</nm:col>
<nm:col nm:cname='THETA8'>0.0000000000000000</nm:col>
<nm:col nm:cname='THETA9'>0.0000000000000000</nm:col>
<nm:col nm:cname='THETA10'>0.0000000000000000</nm:col>
<nm:col nm:cname='THETA11'>0.0000000000000000</nm:col>
<nm:col nm:cname='OMEGA(1,1)'>0.0000000000000000</nm:col>
<nm:col nm:cname='OMEGA(1,2)'>0.0000000000000000</nm:col>
<nm:col nm:cname='OMEGA(1,3)'>0.0000000000000000</nm:col>
<nm:col nm:cname='OMEGA(1,4)'>0.0000000000000000</nm:col>
</nm:row>
<nm:row nm:rname='OMEGA(1,5)'>
<nm:col nm:cname='THETA1'>0.0000000000000000</nm:col>
<nm:col nm:cname='THETA2'>0.0000000000000000</nm:col>
<nm:col nm:cname='THETA3'>0.0000000000000000</nm:col>
<nm:col nm:cname='THETA4'>0.0000000000000000</nm:col>
<nm:col nm:cname='THETA5'>0.0000000000000000</nm:col>
<nm:col nm:cname='THETA6'>0.0000000000000000</nm:col>
<nm:col nm:cname='THETA7'>0.0000000000000000</nm:col>
<nm:col nm:cname='THETA8'>0.0000000000000000</nm:col>
<nm:col nm:cname='THETA9'>0.0000000000000000</nm:col>
<nm:col nm:cname='THETA10'>0.0000000000000000</nm:col>
<nm:col nm:cname='THETA11'>0.0000000000000000</nm:col>
<nm:col nm:cname='OMEGA(1,1)'>0.0000000000000000</nm:col>
<nm:col nm:cname='OMEGA(1,2)'>0.0000000000000000</nm:col>
<nm:col nm:cname='OMEGA(1,3)'>0.0000000000000000</nm:col>
<nm:col nm:cname='OMEGA(1,4)'>0.0000000000000000</nm:col>
<nm:col nm:cname='OMEGA(1,5)'>0.0000000000000000</nm:col>
</nm:row>
<nm:row nm:rname='OMEGA(2,2)'>
<nm:col nm:cname='THETA1'>0.0000000000000000</nm:col>
<nm:col nm:cname='THETA2'>0.0000000000000000</nm:col>
<nm:col nm:cname='THETA3'>0.0000000000000000</nm:col>
<nm:col nm:cname='THETA4'>0.0000000000000000</nm:col>
<nm:col nm:cname='THETA5'>0.0000000000000000</nm:col>
<nm:col nm:cname='THETA6'>0.0000000000000000</nm:col>
<nm:col nm:cname='THETA7'>0.0000000000000000</nm:col>
<nm:col nm:cname='THETA8'>0.0000000000000000</nm:col>
<nm:col nm:cname='THETA9'>0.0000000000000000</nm:col>
<nm:col nm:cname='THETA10'>0.0000000000000000</nm:col>
<nm:col nm:cname='THETA11'>0.0000000000000000</nm:col>
<nm:col nm:cname='OMEGA(1,1)'>0.0000000000000000</nm:col>
<nm:col nm:cname='OMEGA(1,2)'>0.0000000000000000</nm:col>
<nm:col nm:cname='OMEGA(1,3)'>0.0000000000000000</nm:col>
<nm:col nm:cname='OMEGA(1,4)'>0.0000000000000000</nm:col>
<nm:col nm:cname='OMEGA(1,5)'>0.0000000000000000</nm:col>
<nm:col nm:cname='OMEGA(2,2)'>0.0000000000000000</nm:col>
</nm:row>
<nm:row nm:rname='OMEGA(2,3)'>
<nm:col nm:cname='THETA1'>0.0000000000000000</nm:col>
<nm:col nm:cname='THETA2'>0.0000000000000000</nm:col>
<nm:col nm:cname='THETA3'>0.0000000000000000</nm:col>
<nm:col nm:cname='THETA4'>0.0000000000000000</nm:col>
<nm:col nm:cname='THETA5'>0.0000000000000000</nm:col>
<nm:col nm:cname='THETA6'>0.0000000000000000</nm:col>
<nm:col nm:cname='THETA7'>0.0000000000000000</nm:col>
<nm:col nm:cname='THETA8'>0.0000000000000000</nm:col>
<nm:col nm:cname='THETA9'>0.0000000000000000</nm:col>
<nm:col nm:cname='THETA10'>0.0000000000000000</nm:col>
<nm:col nm:cname='THETA11'>0.0000000000000000</nm:col>
<nm:col nm:cname='OMEGA(1,1)'>0.0000000000000000</nm:col>
<nm:col nm:cname='OMEGA(1,2)'>0.0000000000000000</nm:col>
<nm:col nm:cname='OMEGA(1,3)'>0.0000000000000000</nm:col>
<nm:col nm:cname='OMEGA(1,4)'>0.0000000000000000</nm:col>
<nm:col nm:cname='OMEGA(1,5)'>0.0000000000000000</nm:col>
<nm:col nm:cname='OMEGA(2,2)'>0.0000000000000000</nm:col>
<nm:col nm:cname='OMEGA(2,3)'>0.0000000000000000</nm:col>
</nm:row>
<nm:row nm:rname='OMEGA(2,4)'>
<nm:col nm:cname='THETA1'>0.0000000000000000</nm:col>
<nm:col nm:cname='THETA2'>0.0000000000000000</nm:col>
<nm:col nm:cname='THETA3'>0.0000000000000000</nm:col>
<nm:col nm:cname='THETA4'>0.0000000000000000</nm:col>
<nm:col nm:cname='THETA5'>0.0000000000000000</nm:col>
<nm:col nm:cname='THETA6'>0.0000000000000000</nm:col>
<nm:col nm:cname='THETA7'>0.0000000000000000</nm:col>
<nm:col nm:cname='THETA8'>0.0000000000000000</nm:col>
<nm:col nm:cname='THETA9'>0.0000000000000000</nm:col>
<nm:col nm:cname='THETA10'>0.0000000000000000</nm:col>
<nm:col nm:cname='THETA11'>0.0000000000000000</nm:col>
<nm:col nm:cname='OMEGA(1,1)'>0.0000000000000000</nm:col>
<nm:col nm:cname='OMEGA(1,2)'>0.0000000000000000</nm:col>
<nm:col nm:cname='OMEGA(1,3)'>0.0000000000000000</nm:col>
<nm:col nm:cname='OMEGA(1,4)'>0.0000000000000000</nm:col>
<nm:col nm:cname='OMEGA(1,5)'>0.0000000000000000</nm:col>
<nm:col nm:cname='OMEGA(2,2)'>0.0000000000000000</nm:col>
<nm:col nm:cname='OMEGA(2,3)'>0.0000000000000000</nm:col>
<nm:col nm:cname='OMEGA(2,4)'>0.0000000000000000</nm:col>
</nm:row>
<nm:row nm:rname='OMEGA(2,5)'>
<nm:col nm:cname='THETA1'>0.0000000000000000</nm:col>
<nm:col nm:cname='THETA2'>0.0000000000000000</nm:col>
<nm:col nm:cname='THETA3'>0.0000000000000000</nm:col>
<nm:col nm:cname='THETA4'>0.0000000000000000</nm:col>
<nm:col nm:cname='THETA5'>0.0000000000000000</nm:col>
<nm:col nm:cname='THETA6'>0.0000000000000000</nm:col>
<nm:col nm:cname='THETA7'>0.0000000000000000</nm:col>
<nm:col nm:cname='THETA8'>0.0000000000000000</nm:col>
<nm:col nm:cname='THETA9'>0.0000000000000000</nm:col>
<nm:col nm:cname='THETA10'>0.0000000000000000</nm:col>
<nm:col nm:cname='THETA11'>0.0000000000000000</nm:col>
<nm:col nm:cname='OMEGA(1,1)'>0.0000000000000000</nm:col>
<nm:col nm:cname='OMEGA(1,2)'>0.0000000000000000</nm:col>
<nm:col nm:cname='OMEGA(1,3)'>0.0000000000000000</nm:col>
<nm:col nm:cname='OMEGA(1,4)'>0.0000000000000000</nm:col>
<nm:col nm:cname='OMEGA(1,5)'>0.0000000000000000</nm:col>
<nm:col nm:cname='OMEGA(2,2)'>0.0000000000000000</nm:col>
<nm:col nm:cname='OMEGA(2,3)'>0.0000000000000000</nm:col>
<nm:col nm:cname='OMEGA(2,4)'>0.0000000000000000</nm:col>
<nm:col nm:cname='OMEGA(2,5)'>0.0000000000000000</nm:col>
</nm:row>
<nm:row nm:rname='OMEGA(3,3)'>
<nm:col nm:cname='THETA1'>0.0000000000000000</nm:col>
<nm:col nm:cname='THETA2'>0.0000000000000000</nm:col>
<nm:col nm:cname='THETA3'>0.0000000000000000</nm:col>
<nm:col nm:cname='THETA4'>0.0000000000000000</nm:col>
<nm:col nm:cname='THETA5'>0.0000000000000000</nm:col>
<nm:col nm:cname='THETA6'>0.0000000000000000</nm:col>
<nm:col nm:cname='THETA7'>0.0000000000000000</nm:col>
<nm:col nm:cname='THETA8'>0.0000000000000000</nm:col>
<nm:col nm:cname='THETA9'>0.0000000000000000</nm:col>
<nm:col nm:cname='THETA10'>0.0000000000000000</nm:col>
<nm:col nm:cname='THETA11'>0.0000000000000000</nm:col>
<nm:col nm:cname='OMEGA(1,1)'>0.0000000000000000</nm:col>
<nm:col nm:cname='OMEGA(1,2)'>0.0000000000000000</nm:col>
<nm:col nm:cname='OMEGA(1,3)'>0.0000000000000000</nm:col>
<nm:col nm:cname='OMEGA(1,4)'>0.0000000000000000</nm:col>
<nm:col nm:cname='OMEGA(1,5)'>0.0000000000000000</nm:col>
<nm:col nm:cname='OMEGA(2,2)'>0.0000000000000000</nm:col>
<nm:col nm:cname='OMEGA(2,3)'>0.0000000000000000</nm:col>
<nm:col nm:cname='OMEGA(2,4)'>0.0000000000000000</nm:col>
<nm:col nm:cname='OMEGA(2,5)'>0.0000000000000000</nm:col>
<nm:col nm:cname='OMEGA(3,3)'>0.0000000000000000</nm:col>
</nm:row>
<nm:row nm:rname='OMEGA(3,4)'>
<nm:col nm:cname='THETA1'>0.0000000000000000</nm:col>
<nm:col nm:cname='THETA2'>0.0000000000000000</nm:col>
<nm:col nm:cname='THETA3'>0.0000000000000000</nm:col>
<nm:col nm:cname='THETA4'>0.0000000000000000</nm:col>
<nm:col nm:cname='THETA5'>0.0000000000000000</nm:col>
<nm:col nm:cname='THETA6'>0.0000000000000000</nm:col>
<nm:col nm:cname='THETA7'>0.0000000000000000</nm:col>
<nm:col nm:cname='THETA8'>0.0000000000000000</nm:col>
<nm:col nm:cname='THETA9'>0.0000000000000000</nm:col>
<nm:col nm:cname='THETA10'>0.0000000000000000</nm:col>
<nm:col nm:cname='THETA11'>0.0000000000000000</nm:col>
<nm:col nm:cname='OMEGA(1,1)'>0.0000000000000000</nm:col>
<nm:col nm:cname='OMEGA(1,2)'>0.0000000000000000</nm:col>
<nm:col nm:cname='OMEGA(1,3)'>0.0000000000000000</nm:col>
<nm:col nm:cname='OMEGA(1,4)'>0.0000000000000000</nm:col>
<nm:col nm:cname='OMEGA(1,5)'>0.0000000000000000</nm:col>
<nm:col nm:cname='OMEGA(2,2)'>0.0000000000000000</nm:col>
<nm:col nm:cname='OMEGA(2,3)'>0.0000000000000000</nm:col>
<nm:col nm:cname='OMEGA(2,4)'>0.0000000000000000</nm:col>
<nm:col nm:cname='OMEGA(2,5)'>0.0000000000000000</nm:col>
<nm:col nm:cname='OMEGA(3,3)'>0.0000000000000000</nm:col>
<nm:col nm:cname='OMEGA(3,4)'>0.0000000000000000</nm:col>
</nm:row>
<nm:row nm:rname='OMEGA(3,5)'>
<nm:col nm:cname='THETA1'>0.0000000000000000</nm:col>
<nm:col nm:cname='THETA2'>0.0000000000000000</nm:col>
<nm:col nm:cname='THETA3'>0.0000000000000000</nm:col>
<nm:col nm:cname='THETA4'>0.0000000000000000</nm:col>
<nm:col nm:cname='THETA5'>0.0000000000000000</nm:col>
<nm:col nm:cname='THETA6'>0.0000000000000000</nm:col>
<nm:col nm:cname='THETA7'>0.0000000000000000</nm:col>
<nm:col nm:cname='THETA8'>0.0000000000000000</nm:col>
<nm:col nm:cname='THETA9'>0.0000000000000000</nm:col>
<nm:col nm:cname='THETA10'>0.0000000000000000</nm:col>
<nm:col nm:cname='THETA11'>0.0000000000000000</nm:col>
<nm:col nm:cname='OMEGA(1,1)'>0.0000000000000000</nm:col>
<nm:col nm:cname='OMEGA(1,2)'>0.0000000000000000</nm:col>
<nm:col nm:cname='OMEGA(1,3)'>0.0000000000000000</nm:col>
<nm:col nm:cname='OMEGA(1,4)'>0.0000000000000000</nm:col>
<nm:col nm:cname='OMEGA(1,5)'>0.0000000000000000</nm:col>
<nm:col nm:cname='OMEGA(2,2)'>0.0000000000000000</nm:col>
<nm:col nm:cname='OMEGA(2,3)'>0.0000000000000000</nm:col>
<nm:col nm:cname='OMEGA(2,4)'>0.0000000000000000</nm:col>
<nm:col nm:cname='OMEGA(2,5)'>0.0000000000000000</nm:col>
<nm:col nm:cname='OMEGA(3,3)'>0.0000000000000000</nm:col>
<nm:col nm:cname='OMEGA(3,4)'>0.0000000000000000</nm:col>
<nm:col nm:cname='OMEGA(3,5)'>0.0000000000000000</nm:col>
</nm:row>
<nm:row nm:rname='OMEGA(4,4)'>
<nm:col nm:cname='THETA1'>0.0000000000000000</nm:col>
<nm:col nm:cname='THETA2'>0.0000000000000000</nm:col>
<nm:col nm:cname='THETA3'>0.0000000000000000</nm:col>
<nm:col nm:cname='THETA4'>0.0000000000000000</nm:col>
<nm:col nm:cname='THETA5'>0.0000000000000000</nm:col>
<nm:col nm:cname='THETA6'>0.0000000000000000</nm:col>
<nm:col nm:cname='THETA7'>0.0000000000000000</nm:col>
<nm:col nm:cname='THETA8'>0.0000000000000000</nm:col>
<nm:col nm:cname='THETA9'>0.0000000000000000</nm:col>
<nm:col nm:cname='THETA10'>0.0000000000000000</nm:col>
<nm:col nm:cname='THETA11'>0.0000000000000000</nm:col>
<nm:col nm:cname='OMEGA(1,1)'>0.0000000000000000</nm:col>
<nm:col nm:cname='OMEGA(1,2)'>0.0000000000000000</nm:col>
<nm:col nm:cname='OMEGA(1,3)'>0.0000000000000000</nm:col>
<nm:col nm:cname='OMEGA(1,4)'>0.0000000000000000</nm:col>
<nm:col nm:cname='OMEGA(1,5)'>0.0000000000000000</nm:col>
<nm:col nm:cname='OMEGA(2,2)'>0.0000000000000000</nm:col>
<nm:col nm:cname='OMEGA(2,3)'>0.0000000000000000</nm:col>
<nm:col nm:cname='OMEGA(2,4)'>0.0000000000000000</nm:col>
<nm:col nm:cname='OMEGA(2,5)'>0.0000000000000000</nm:col>
<nm:col nm:cname='OMEGA(3,3)'>0.0000000000000000</nm:col>
<nm:col nm:cname='OMEGA(3,4)'>0.0000000000000000</nm:col>
<nm:col nm:cname='OMEGA(3,5)'>0.0000000000000000</nm:col>
<nm:col nm:cname='OMEGA(4,4)'>0.0000000000000000</nm:col>
</nm:row>
<nm:row nm:rname='OMEGA(4,5)'>
<nm:col nm:cname='THETA1'>0.0000000000000000</nm:col>
<nm:col nm:cname='THETA2'>0.0000000000000000</nm:col>
<nm:col nm:cname='THETA3'>0.0000000000000000</nm:col>
<nm:col nm:cname='THETA4'>0.0000000000000000</nm:col>
<nm:col nm:cname='THETA5'>0.0000000000000000</nm:col>
<nm:col nm:cname='THETA6'>0.0000000000000000</nm:col>
<nm:col nm:cname='THETA7'>0.0000000000000000</nm:col>
<nm:col nm:cname='THETA8'>0.0000000000000000</nm:col>
<nm:col nm:cname='THETA9'>0.0000000000000000</nm:col>
<nm:col nm:cname='THETA10'>0.0000000000000000</nm:col>
<nm:col nm:cname='THETA11'>0.0000000000000000</nm:col>
<nm:col nm:cname='OMEGA(1,1)'>0.0000000000000000</nm:col>
<nm:col nm:cname='OMEGA(1,2)'>0.0000000000000000</nm:col>
<nm:col nm:cname='OMEGA(1,3)'>0.0000000000000000</nm:col>
<nm:col nm:cname='OMEGA(1,4)'>0.0000000000000000</nm:col>
<nm:col nm:cname='OMEGA(1,5)'>0.0000000000000000</nm:col>
<nm:col nm:cname='OMEGA(2,2)'>0.0000000000000000</nm:col>
<nm:col nm:cname='OMEGA(2,3)'>0.0000000000000000</nm:col>
<nm:col nm:cname='OMEGA(2,4)'>0.0000000000000000</nm:col>
<nm:col nm:cname='OMEGA(2,5)'>0.0000000000000000</nm:col>
<nm:col nm:cname='OMEGA(3,3)'>0.0000000000000000</nm:col>
<nm:col nm:cname='OMEGA(3,4)'>0.0000000000000000</nm:col>
<nm:col nm:cname='OMEGA(3,5)'>0.0000000000000000</nm:col>
<nm:col nm:cname='OMEGA(4,4)'>0.0000000000000000</nm:col>
<nm:col nm:cname='OMEGA(4,5)'>0.0000000000000000</nm:col>
</nm:row>
<nm:row nm:rname='OMEGA(5,5)'>
<nm:col nm:cname='THETA1'>0.0000000000000000</nm:col>
<nm:col nm:cname='THETA2'>0.0000000000000000</nm:col>
<nm:col nm:cname='THETA3'>0.0000000000000000</nm:col>
<nm:col nm:cname='THETA4'>0.0000000000000000</nm:col>
<nm:col nm:cname='THETA5'>0.0000000000000000</nm:col>
<nm:col nm:cname='THETA6'>0.0000000000000000</nm:col>
<nm:col nm:cname='THETA7'>0.0000000000000000</nm:col>
<nm:col nm:cname='THETA8'>0.0000000000000000</nm:col>
<nm:col nm:cname='THETA9'>0.0000000000000000</nm:col>
<nm:col nm:cname='THETA10'>0.0000000000000000</nm:col>
<nm:col nm:cname='THETA11'>0.0000000000000000</nm:col>
<nm:col nm:cname='OMEGA(1,1)'>0.0000000000000000</nm:col>
<nm:col nm:cname='OMEGA(1,2)'>0.0000000000000000</nm:col>
<nm:col nm:cname='OMEGA(1,3)'>0.0000000000000000</nm:col>
<nm:col nm:cname='OMEGA(1,4)'>0.0000000000000000</nm:col>
<nm:col nm:cname='OMEGA(1,5)'>0.0000000000000000</nm:col>
<nm:col nm:cname='OMEGA(2,2)'>0.0000000000000000</nm:col>
<nm:col nm:cname='OMEGA(2,3)'>0.0000000000000000</nm:col>
<nm:col nm:cname='OMEGA(2,4)'>0.0000000000000000</nm:col>
<nm:col nm:cname='OMEGA(2,5)'>0.0000000000000000</nm:col>
<nm:col nm:cname='OMEGA(3,3)'>0.0000000000000000</nm:col>
<nm:col nm:cname='OMEGA(3,4)'>0.0000000000000000</nm:col>
<nm:col nm:cname='OMEGA(3,5)'>0.0000000000000000</nm:col>
<nm:col nm:cname='OMEGA(4,4)'>0.0000000000000000</nm:col>
<nm:col nm:cname='OMEGA(4,5)'>0.0000000000000000</nm:col>
<nm:col nm:cname='OMEGA(5,5)'>0.0000000000000000</nm:col>
</nm:row>
<nm:row nm:rname='SIGMA(1,1)'>
<nm:col nm:cname='THETA1'>0.0000000000000000</nm:col>
<nm:col nm:cname='THETA2'>0.0000000000000000</nm:col>
<nm:col nm:cname='THETA3'>0.0000000000000000</nm:col>
<nm:col nm:cname='THETA4'>0.0000000000000000</nm:col>
<nm:col nm:cname='THETA5'>0.0000000000000000</nm:col>
<nm:col nm:cname='THETA6'>0.0000000000000000</nm:col>
<nm:col nm:cname='THETA7'>0.0000000000000000</nm:col>
<nm:col nm:cname='THETA8'>0.0000000000000000</nm:col>
<nm:col nm:cname='THETA9'>0.0000000000000000</nm:col>
<nm:col nm:cname='THETA10'>0.0000000000000000</nm:col>
<nm:col nm:cname='THETA11'>0.0000000000000000</nm:col>
<nm:col nm:cname='OMEGA(1,1)'>0.0000000000000000</nm:col>
<nm:col nm:cname='OMEGA(1,2)'>0.0000000000000000</nm:col>
<nm:col nm:cname='OMEGA(1,3)'>0.0000000000000000</nm:col>
<nm:col nm:cname='OMEGA(1,4)'>0.0000000000000000</nm:col>
<nm:col nm:cname='OMEGA(1,5)'>0.0000000000000000</nm:col>
<nm:col nm:cname='OMEGA(2,2)'>0.0000000000000000</nm:col>
<nm:col nm:cname='OMEGA(2,3)'>0.0000000000000000</nm:col>
<nm:col nm:cname='OMEGA(2,4)'>0.0000000000000000</nm:col>
<nm:col nm:cname='OMEGA(2,5)'>0.0000000000000000</nm:col>
<nm:col nm:cname='OMEGA(3,3)'>0.0000000000000000</nm:col>
<nm:col nm:cname='OMEGA(3,4)'>0.0000000000000000</nm:col>
<nm:col nm:cname='OMEGA(3,5)'>0.0000000000000000</nm:col>
<nm:col nm:cname='OMEGA(4,4)'>0.0000000000000000</nm:col>
<nm:col nm:cname='OMEGA(4,5)'>0.0000000000000000</nm:col>
<nm:col nm:cname='OMEGA(5,5)'>0.0000000000000000</nm:col>
<nm:col nm:cname='SIGMA(1,1)'>0.0000000000000000</nm:col>
</nm:row>
</nm:invcovariance>
</nm:estimation>
<nm:post_process_times>
<nm:post_elapsed_time>0.00</nm:post_elapsed_time>
<nm:finaloutput_elapsed_time>0.03</nm:finaloutput_elapsed_time>
</nm:post_process_times>
</nm:problem>
</nm:nonmem>
<nm:stop_datetime>2021-09-28T21:36:32.407</nm:stop_datetime>
<nm:total_cputime>28.401</nm:total_cputime>
</nm:output>
